[{"id":2,"ref_id":"656ef76a0373e","document_type_id":1,"user_id":11,"user_info_id":1,"path":"656ef76a0373e.pdf","pushed":1,"created_at":"2023-12-05T10:11:54.000000Z","updated_at":"2023-12-11T06:14:54.000000Z","user":{"id":11,"name":"Test User","email":"test@example.com","email_verified_at":"2023-12-05T10:10:27.000000Z","two_factor_confirmed_at":null,"current_team_id":null,"profile_photo_path":null,"created_at":"2023-12-05T10:10:27.000000Z","updated_at":"2023-12-05T10:10:27.000000Z","profile_photo_url":"https:\/\/ui-avatars.com\/api\/?name=T+U&color=7F9CF5&background=EBF4FF"},"user_info":{"id":1,"firstname":"John","lastname":"Doe","middlename":"N\/A","contact":"093289743874","birthdate":"2023-12-10","address":"poruih wenwjs gg","created_at":"2023-12-05T10:11:02.000000Z","updated_at":"2023-12-05T10:11:02.000000Z","full_name":"John Doe"},"document_type":{"id":1,"name":"Certificate of Grades","created_at":"2023-12-05T10:11:17.000000Z","updated_at":"2023-12-05T10:11:17.000000Z"}},{"id":3,"ref_id":"656ef9917c3c5","document_type_id":1,"user_id":11,"user_info_id":1,"path":"656ef9917c3c5.pdf","pushed":1,"created_at":"2023-12-05T10:21:05.000000Z","updated_at":"2023-12-11T06:14:54.000000Z","user":{"id":11,"name":"Test User","email":"test@example.com","email_verified_at":"2023-12-05T10:10:27.000000Z","two_factor_confirmed_at":null,"current_team_id":null,"profile_photo_path":null,"created_at":"2023-12-05T10:10:27.000000Z","updated_at":"2023-12-05T10:10:27.000000Z","profile_photo_url":"https:\/\/ui-avatars.com\/api\/?name=T+U&color=7F9CF5&background=EBF4FF"},"user_info":{"id":1,"firstname":"John","lastname":"Doe","middlename":"N\/A","contact":"093289743874","birthdate":"2023-12-10","address":"poruih wenwjs gg","created_at":"2023-12-05T10:11:02.000000Z","updated_at":"2023-12-05T10:11:02.000000Z","full_name":"John Doe"},"document_type":{"id":1,"name":"Certificate of Grades","created_at":"2023-12-05T10:11:17.000000Z","updated_at":"2023-12-05T10:11:17.000000Z"}},{"id":4,"ref_id":"656f03c288a5b","document_type_id":1,"user_id":11,"user_info_id":1,"path":"656f03c288a5b.pdf","pushed":1,"created_at":"2023-12-05T11:04:34.000000Z","updated_at":"2023-12-11T06:14:54.000000Z","user":{"id":11,"name":"Test User","email":"test@example.com","email_verified_at":"2023-12-05T10:10:27.000000Z","two_factor_confirmed_at":null,"current_team_id":null,"profile_photo_path":null,"created_at":"2023-12-05T10:10:27.000000Z","updated_at":"2023-12-05T10:10:27.000000Z","profile_photo_url":"https:\/\/ui-avatars.com\/api\/?name=T+U&color=7F9CF5&background=EBF4FF"},"user_info":{"id":1,"firstname":"John","lastname":"Doe","middlename":"N\/A","contact":"093289743874","birthdate":"2023-12-10","address":"poruih wenwjs gg","created_at":"2023-12-05T10:11:02.000000Z","updated_at":"2023-12-05T10:11:02.000000Z","full_name":"John Doe"},"document_type":{"id":1,"name":"Certificate of Grades","created_at":"2023-12-05T10:11:17.000000Z","updated_at":"2023-12-05T10:11:17.000000Z"}},{"id":5,"ref_id":"656f091b9aac5","document_type_id":2,"user_id":11,"user_info_id":2,"path":"656f091b9aac5.pdf","pushed":1,"created_at":"2023-12-05T11:27:23.000000Z","updated_at":"2023-12-11T06:14:55.000000Z","user":{"id":11,"name":"Test User","email":"test@example.com","email_verified_at":"2023-12-05T10:10:27.000000Z","two_factor_confirmed_at":null,"current_team_id":null,"profile_photo_path":null,"created_at":"2023-12-05T10:10:27.000000Z","updated_at":"2023-12-05T10:10:27.000000Z","profile_photo_url":"https:\/\/ui-avatars.com\/api\/?name=T+U&color=7F9CF5&background=EBF4FF"},"user_info":{"id":2,"firstname":"Ruseel","lastname":"Mercado","middlename":"M.","contact":"34142421","birthdate":"2023-12-05","address":"pneranda","created_at":"2023-12-05T11:26:15.000000Z","updated_at":"2023-12-05T11:26:15.000000Z","full_name":"Ruseel Mercado M."},"document_type":{"id":2,"name":"Certificate of Enrollment","created_at":"2023-12-05T11:26:50.000000Z","updated_at":"2023-12-05T11:26:50.000000Z"}},{"id":6,"ref_id":"6576a0eadc7b6","document_type_id":1,"user_id":12,"user_info_id":2,"path":"6576a0eadc7b6.pdf","pushed":1,"created_at":"2023-12-11T05:40:58.000000Z","updated_at":"2023-12-11T06:14:55.000000Z","user":{"id":12,"name":"BossRussel","email":"mercadojohnrussel00@gmail.com","email_verified_at":null,"two_factor_confirmed_at":null,"current_team_id":null,"profile_photo_path":null,"created_at":"2023-12-11T05:40:07.000000Z","updated_at":"2023-12-11T05:40:07.000000Z","profile_photo_url":"https:\/\/ui-avatars.com\/api\/?name=B&color=7F9CF5&background=EBF4FF"},"user_info":{"id":2,"firstname":"Ruseel","lastname":"Mercado","middlename":"M.","contact":"34142421","birthdate":"2023-12-05","address":"pneranda","created_at":"2023-12-05T11:26:15.000000Z","updated_at":"2023-12-05T11:26:15.000000Z","full_name":"Ruseel Mercado M."},"document_type":{"id":1,"name":"Certificate of Grades","created_at":"2023-12-05T10:11:17.000000Z","updated_at":"2023-12-05T10:11:17.000000Z"}},{"id":2,"ref_id":"656ef76a0373e","document_type_id":1,"user_id":11,"user_info_id":1,"path":"656ef76a0373e.pdf","pushed":1,"created_at":"2023-12-05T10:11:54.000000Z","updated_at":"2023-12-11T06:21:43.000000Z","user":{"id":11,"name":"Test User","email":"test@example.com","email_verified_at":"2023-12-05T10:10:27.000000Z","two_factor_confirmed_at":null,"current_team_id":null,"profile_photo_path":null,"created_at":"2023-12-05T10:10:27.000000Z","updated_at":"2023-12-05T10:10:27.000000Z","profile_photo_url":"https:\/\/ui-avatars.com\/api\/?name=T+U&color=7F9CF5&background=EBF4FF"},"user_info":{"id":1,"firstname":"John","lastname":"Doe","middlename":"N\/A","contact":"093289743874","birthdate":"2023-12-10","address":"poruih wenwjs gg","created_at":"2023-12-05T10:11:02.000000Z","updated_at":"2023-12-05T10:11:02.000000Z","full_name":"John Doe"},"document_type":{"id":1,"name":"Certificate of Grades","created_at":"2023-12-05T10:11:17.000000Z","updated_at":"2023-12-05T10:11:17.000000Z"}},{"id":3,"ref_id":"656ef9917c3c5","document_type_id":1,"user_id":11,"user_info_id":1,"path":"656ef9917c3c5.pdf","pushed":1,"created_at":"2023-12-05T10:21:05.000000Z","updated_at":"2023-12-11T06:21:43.000000Z","user":{"id":11,"name":"Test User","email":"test@example.com","email_verified_at":"2023-12-05T10:10:27.000000Z","two_factor_confirmed_at":null,"current_team_id":null,"profile_photo_path":null,"created_at":"2023-12-05T10:10:27.000000Z","updated_at":"2023-12-05T10:10:27.000000Z","profile_photo_url":"https:\/\/ui-avatars.com\/api\/?name=T+U&color=7F9CF5&background=EBF4FF"},"user_info":{"id":1,"firstname":"John","lastname":"Doe","middlename":"N\/A","contact":"093289743874","birthdate":"2023-12-10","address":"poruih wenwjs gg","created_at":"2023-12-05T10:11:02.000000Z","updated_at":"2023-12-05T10:11:02.000000Z","full_name":"John Doe"},"document_type":{"id":1,"name":"Certificate of Grades","created_at":"2023-12-05T10:11:17.000000Z","updated_at":"2023-12-05T10:11:17.000000Z"}},{"id":4,"ref_id":"656f03c288a5b","document_type_id":1,"user_id":11,"user_info_id":1,"path":"656f03c288a5b.pdf","pushed":1,"created_at":"2023-12-05T11:04:34.000000Z","updated_at":"2023-12-11T06:21:43.000000Z","user":{"id":11,"name":"Test User","email":"test@example.com","email_verified_at":"2023-12-05T10:10:27.000000Z","two_factor_confirmed_at":null,"current_team_id":null,"profile_photo_path":null,"created_at":"2023-12-05T10:10:27.000000Z","updated_at":"2023-12-05T10:10:27.000000Z","profile_photo_url":"https:\/\/ui-avatars.com\/api\/?name=T+U&color=7F9CF5&background=EBF4FF"},"user_info":{"id":1,"firstname":"John","lastname":"Doe","middlename":"N\/A","contact":"093289743874","birthdate":"2023-12-10","address":"poruih wenwjs gg","created_at":"2023-12-05T10:11:02.000000Z","updated_at":"2023-12-05T10:11:02.000000Z","full_name":"John Doe"},"document_type":{"id":1,"name":"Certificate of Grades","created_at":"2023-12-05T10:11:17.000000Z","updated_at":"2023-12-05T10:11:17.000000Z"}},{"id":5,"ref_id":"656f091b9aac5","document_type_id":2,"user_id":11,"user_info_id":2,"path":"656f091b9aac5.pdf","pushed":1,"created_at":"2023-12-05T11:27:23.000000Z","updated_at":"2023-12-11T06:21:43.000000Z","user":{"id":11,"name":"Test User","email":"test@example.com","email_verified_at":"2023-12-05T10:10:27.000000Z","two_factor_confirmed_at":null,"current_team_id":null,"profile_photo_path":null,"created_at":"2023-12-05T10:10:27.000000Z","updated_at":"2023-12-05T10:10:27.000000Z","profile_photo_url":"https:\/\/ui-avatars.com\/api\/?name=T+U&color=7F9CF5&background=EBF4FF"},"user_info":{"id":2,"firstname":"Ruseel","lastname":"Mercado","middlename":"M.","contact":"34142421","birthdate":"2023-12-05","address":"pneranda","created_at":"2023-12-05T11:26:15.000000Z","updated_at":"2023-12-05T11:26:15.000000Z","full_name":"Ruseel Mercado M."},"document_type":{"id":2,"name":"Certificate of Enrollment","created_at":"2023-12-05T11:26:50.000000Z","updated_at":"2023-12-05T11:26:50.000000Z"}},{"id":6,"ref_id":"6576a0eadc7b6","document_type_id":1,"user_id":12,"user_info_id":2,"path":"6576a0eadc7b6.pdf","pushed":1,"created_at":"2023-12-11T05:40:58.000000Z","updated_at":"2023-12-11T06:21:43.000000Z","user":{"id":12,"name":"BossRussel","email":"mercadojohnrussel00@gmail.com","email_verified_at":null,"two_factor_confirmed_at":null,"current_team_id":null,"profile_photo_path":null,"created_at":"2023-12-11T05:40:07.000000Z","updated_at":"2023-12-11T05:40:07.000000Z","profile_photo_url":"https:\/\/ui-avatars.com\/api\/?name=B&color=7F9CF5&background=EBF4FF"},"user_info":{"id":2,"firstname":"Ruseel","lastname":"Mercado","middlename":"M.","contact":"34142421","birthdate":"2023-12-05","address":"pneranda","created_at":"2023-12-05T11:26:15.000000Z","updated_at":"2023-12-05T11:26:15.000000Z","full_name":"Ruseel Mercado M."},"document_type":{"id":1,"name":"Certificate of Grades","created_at":"2023-12-05T10:11:17.000000Z","updated_at":"2023-12-05T10:11:17.000000Z"}},{"id":7,"ref_id":"6576aaf01f85d","document_type_id":3,"user_id":12,"user_info_id":1,"path":"6576aaf01f85d.pdf","pushed":0,"created_at":"2023-12-11T06:23:44.000000Z","updated_at":"2023-12-11T06:24:32.000000Z","user":{"id":12,"name":"BossRussel","email":"mercadojohnrussel00@gmail.com","email_verified_at":null,"two_factor_confirmed_at":null,"current_team_id":null,"profile_photo_path":null,"created_at":"2023-12-11T05:40:07.000000Z","updated_at":"2023-12-11T05:40:07.000000Z","profile_photo_url":"https:\/\/ui-avatars.com\/api\/?name=B&color=7F9CF5&background=EBF4FF"},"user_info":{"id":1,"firstname":"John","lastname":"Doe","middlename":"N\/A","contact":"093289743874","birthdate":"2023-12-10","address":"poruih wenwjs gg","created_at":"2023-12-05T10:11:02.000000Z","updated_at":"2023-12-05T10:11:02.000000Z","full_name":"John Doe"},"document_type":{"id":3,"name":"Form 137","created_at":"2023-12-11T06:23:32.000000Z","updated_at":"2023-12-11T06:23:32.000000Z"}},{"id":2,"ref_id":"656ef76a0373e","document_type_id":1,"user_id":11,"user_info_id":1,"path":"656ef76a0373e.pdf","pushed":1,"created_at":"2023-12-05T10:11:54.000000Z","updated_at":"2023-12-11T06:24:48.000000Z","user":{"id":11,"name":"Test User","email":"test@example.com","email_verified_at":"2023-12-05T10:10:27.000000Z","two_factor_confirmed_at":null,"current_team_id":null,"profile_photo_path":null,"created_at":"2023-12-05T10:10:27.000000Z","updated_at":"2023-12-05T10:10:27.000000Z","profile_photo_url":"https:\/\/ui-avatars.com\/api\/?name=T+U&color=7F9CF5&background=EBF4FF"},"user_info":{"id":1,"firstname":"John","lastname":"Doe","middlename":"N\/A","contact":"093289743874","birthdate":"2023-12-10","address":"poruih wenwjs gg","created_at":"2023-12-05T10:11:02.000000Z","updated_at":"2023-12-05T10:11:02.000000Z","full_name":"John Doe"},"document_type":{"id":1,"name":"Certificate of Grades","created_at":"2023-12-05T10:11:17.000000Z","updated_at":"2023-12-05T10:11:17.000000Z"}},{"id":3,"ref_id":"656ef9917c3c5","document_type_id":1,"user_id":11,"user_info_id":1,"path":"656ef9917c3c5.pdf","pushed":1,"created_at":"2023-12-05T10:21:05.000000Z","updated_at":"2023-12-11T06:24:48.000000Z","user":{"id":11,"name":"Test User","email":"test@example.com","email_verified_at":"2023-12-05T10:10:27.000000Z","two_factor_confirmed_at":null,"current_team_id":null,"profile_photo_path":null,"created_at":"2023-12-05T10:10:27.000000Z","updated_at":"2023-12-05T10:10:27.000000Z","profile_photo_url":"https:\/\/ui-avatars.com\/api\/?name=T+U&color=7F9CF5&background=EBF4FF"},"user_info":{"id":1,"firstname":"John","lastname":"Doe","middlename":"N\/A","contact":"093289743874","birthdate":"2023-12-10","address":"poruih wenwjs gg","created_at":"2023-12-05T10:11:02.000000Z","updated_at":"2023-12-05T10:11:02.000000Z","full_name":"John Doe"},"document_type":{"id":1,"name":"Certificate of Grades","created_at":"2023-12-05T10:11:17.000000Z","updated_at":"2023-12-05T10:11:17.000000Z"}},{"id":4,"ref_id":"656f03c288a5b","document_type_id":1,"user_id":11,"user_info_id":1,"path":"656f03c288a5b.pdf","pushed":1,"created_at":"2023-12-05T11:04:34.000000Z","updated_at":"2023-12-11T06:24:48.000000Z","user":{"id":11,"name":"Test User","email":"test@example.com","email_verified_at":"2023-12-05T10:10:27.000000Z","two_factor_confirmed_at":null,"current_team_id":null,"profile_photo_path":null,"created_at":"2023-12-05T10:10:27.000000Z","updated_at":"2023-12-05T10:10:27.000000Z","profile_photo_url":"https:\/\/ui-avatars.com\/api\/?name=T+U&color=7F9CF5&background=EBF4FF"},"user_info":{"id":1,"firstname":"John","lastname":"Doe","middlename":"N\/A","contact":"093289743874","birthdate":"2023-12-10","address":"poruih wenwjs gg","created_at":"2023-12-05T10:11:02.000000Z","updated_at":"2023-12-05T10:11:02.000000Z","full_name":"John Doe"},"document_type":{"id":1,"name":"Certificate of Grades","created_at":"2023-12-05T10:11:17.000000Z","updated_at":"2023-12-05T10:11:17.000000Z"}},{"id":5,"ref_id":"656f091b9aac5","document_type_id":2,"user_id":11,"user_info_id":2,"path":"656f091b9aac5.pdf","pushed":1,"created_at":"2023-12-05T11:27:23.000000Z","updated_at":"2023-12-11T06:24:49.000000Z","user":{"id":11,"name":"Test User","email":"test@example.com","email_verified_at":"2023-12-05T10:10:27.000000Z","two_factor_confirmed_at":null,"current_team_id":null,"profile_photo_path":null,"created_at":"2023-12-05T10:10:27.000000Z","updated_at":"2023-12-05T10:10:27.000000Z","profile_photo_url":"https:\/\/ui-avatars.com\/api\/?name=T+U&color=7F9CF5&background=EBF4FF"},"user_info":{"id":2,"firstname":"Ruseel","lastname":"Mercado","middlename":"M.","contact":"34142421","birthdate":"2023-12-05","address":"pneranda","created_at":"2023-12-05T11:26:15.000000Z","updated_at":"2023-12-05T11:26:15.000000Z","full_name":"Ruseel Mercado M."},"document_type":{"id":2,"name":"Certificate of Enrollment","created_at":"2023-12-05T11:26:50.000000Z","updated_at":"2023-12-05T11:26:50.000000Z"}},{"id":6,"ref_id":"6576a0eadc7b6","document_type_id":1,"user_id":12,"user_info_id":2,"path":"6576a0eadc7b6.pdf","pushed":1,"created_at":"2023-12-11T05:40:58.000000Z","updated_at":"2023-12-11T06:24:49.000000Z","user":{"id":12,"name":"BossRussel","email":"mercadojohnrussel00@gmail.com","email_verified_at":null,"two_factor_confirmed_at":null,"current_team_id":null,"profile_photo_path":null,"created_at":"2023-12-11T05:40:07.000000Z","updated_at":"2023-12-11T05:40:07.000000Z","profile_photo_url":"https:\/\/ui-avatars.com\/api\/?name=B&color=7F9CF5&background=EBF4FF"},"user_info":{"id":2,"firstname":"Ruseel","lastname":"Mercado","middlename":"M.","contact":"34142421","birthdate":"2023-12-05","address":"pneranda","created_at":"2023-12-05T11:26:15.000000Z","updated_at":"2023-12-05T11:26:15.000000Z","full_name":"Ruseel Mercado M."},"document_type":{"id":1,"name":"Certificate of Grades","created_at":"2023-12-05T10:11:17.000000Z","updated_at":"2023-12-05T10:11:17.000000Z"}},{"id":7,"ref_id":"6576aaf01f85d","document_type_id":3,"user_id":12,"user_info_id":1,"path":"6576aaf01f85d.pdf","pushed":1,"created_at":"2023-12-11T06:23:44.000000Z","updated_at":"2023-12-11T06:24:49.000000Z","user":{"id":12,"name":"BossRussel","email":"mercadojohnrussel00@gmail.com","email_verified_at":null,"two_factor_confirmed_at":null,"current_team_id":null,"profile_photo_path":null,"created_at":"2023-12-11T05:40:07.000000Z","updated_at":"2023-12-11T05:40:07.000000Z","profile_photo_url":"https:\/\/ui-avatars.com\/api\/?name=B&color=7F9CF5&background=EBF4FF"},"user_info":{"id":1,"firstname":"John","lastname":"Doe","middlename":"N\/A","contact":"093289743874","birthdate":"2023-12-10","address":"poruih wenwjs gg","created_at":"2023-12-05T10:11:02.000000Z","updated_at":"2023-12-05T10:11:02.000000Z","full_name":"John Doe"},"document_type":{"id":3,"name":"Form 137","created_at":"2023-12-11T06:23:32.000000Z","updated_at":"2023-12-11T06:23:32.000000Z"}},{"id":8,"ref_id":"6576ade17ff35","document_type_id":1,"user_id":12,"user_info_id":2,"path":"6576ade17ff35.pdf","pushed":0,"created_at":"2023-12-11T06:36:17.000000Z","updated_at":"2023-12-11T06:36:19.000000Z","user":{"id":12,"name":"BossRussel","email":"mercadojohnrussel00@gmail.com","email_verified_at":null,"two_factor_confirmed_at":null,"current_team_id":null,"profile_photo_path":null,"created_at":"2023-12-11T05:40:07.000000Z","updated_at":"2023-12-11T05:40:07.000000Z","profile_photo_url":"https:\/\/ui-avatars.com\/api\/?name=B&color=7F9CF5&background=EBF4FF"},"user_info":{"id":2,"firstname":"Ruseel","lastname":"Mercado","middlename":"M.","contact":"34142421","birthdate":"2023-12-05","address":"pneranda","created_at":"2023-12-05T11:26:15.000000Z","updated_at":"2023-12-05T11:26:15.000000Z","full_name":"Ruseel Mercado M."},"document_type":{"id":1,"name":"Certificate of Grades","created_at":"2023-12-05T10:11:17.000000Z","updated_at":"2023-12-05T10:11:17.000000Z"}},{"id":2,"ref_id":"656ef76a0373e","document_type_id":1,"user_id":11,"user_info_id":1,"path":"656ef76a0373e.pdf","pushed":1,"created_at":"2023-12-05T10:11:54.000000Z","updated_at":"2023-12-11T06:36:25.000000Z","user":{"id":11,"name":"Test User","email":"test@example.com","email_verified_at":"2023-12-05T10:10:27.000000Z","two_factor_confirmed_at":null,"current_team_id":null,"profile_photo_path":null,"created_at":"2023-12-05T10:10:27.000000Z","updated_at":"2023-12-05T10:10:27.000000Z","profile_photo_url":"https:\/\/ui-avatars.com\/api\/?name=T+U&color=7F9CF5&background=EBF4FF"},"user_info":{"id":1,"firstname":"John","lastname":"Doe","middlename":"N\/A","contact":"093289743874","birthdate":"2023-12-10","address":"poruih wenwjs gg","created_at":"2023-12-05T10:11:02.000000Z","updated_at":"2023-12-05T10:11:02.000000Z","full_name":"John Doe"},"document_type":{"id":1,"name":"Certificate of Grades","created_at":"2023-12-05T10:11:17.000000Z","updated_at":"2023-12-05T10:11:17.000000Z"}},{"id":3,"ref_id":"656ef9917c3c5","document_type_id":1,"user_id":11,"user_info_id":1,"path":"656ef9917c3c5.pdf","pushed":1,"created_at":"2023-12-05T10:21:05.000000Z","updated_at":"2023-12-11T06:36:25.000000Z","user":{"id":11,"name":"Test User","email":"test@example.com","email_verified_at":"2023-12-05T10:10:27.000000Z","two_factor_confirmed_at":null,"current_team_id":null,"profile_photo_path":null,"created_at":"2023-12-05T10:10:27.000000Z","updated_at":"2023-12-05T10:10:27.000000Z","profile_photo_url":"https:\/\/ui-avatars.com\/api\/?name=T+U&color=7F9CF5&background=EBF4FF"},"user_info":{"id":1,"firstname":"John","lastname":"Doe","middlename":"N\/A","contact":"093289743874","birthdate":"2023-12-10","address":"poruih wenwjs gg","created_at":"2023-12-05T10:11:02.000000Z","updated_at":"2023-12-05T10:11:02.000000Z","full_name":"John Doe"},"document_type":{"id":1,"name":"Certificate of Grades","created_at":"2023-12-05T10:11:17.000000Z","updated_at":"2023-12-05T10:11:17.000000Z"}},{"id":4,"ref_id":"656f03c288a5b","document_type_id":1,"user_id":11,"user_info_id":1,"path":"656f03c288a5b.pdf","pushed":1,"created_at":"2023-12-05T11:04:34.000000Z","updated_at":"2023-12-11T06:36:25.000000Z","user":{"id":11,"name":"Test User","email":"test@example.com","email_verified_at":"2023-12-05T10:10:27.000000Z","two_factor_confirmed_at":null,"current_team_id":null,"profile_photo_path":null,"created_at":"2023-12-05T10:10:27.000000Z","updated_at":"2023-12-05T10:10:27.000000Z","profile_photo_url":"https:\/\/ui-avatars.com\/api\/?name=T+U&color=7F9CF5&background=EBF4FF"},"user_info":{"id":1,"firstname":"John","lastname":"Doe","middlename":"N\/A","contact":"093289743874","birthdate":"2023-12-10","address":"poruih wenwjs gg","created_at":"2023-12-05T10:11:02.000000Z","updated_at":"2023-12-05T10:11:02.000000Z","full_name":"John Doe"},"document_type":{"id":1,"name":"Certificate of Grades","created_at":"2023-12-05T10:11:17.000000Z","updated_at":"2023-12-05T10:11:17.000000Z"}},{"id":5,"ref_id":"656f091b9aac5","document_type_id":2,"user_id":11,"user_info_id":2,"path":"656f091b9aac5.pdf","pushed":1,"created_at":"2023-12-05T11:27:23.000000Z","updated_at":"2023-12-11T06:36:25.000000Z","user":{"id":11,"name":"Test User","email":"test@example.com","email_verified_at":"2023-12-05T10:10:27.000000Z","two_factor_confirmed_at":null,"current_team_id":null,"profile_photo_path":null,"created_at":"2023-12-05T10:10:27.000000Z","updated_at":"2023-12-05T10:10:27.000000Z","profile_photo_url":"https:\/\/ui-avatars.com\/api\/?name=T+U&color=7F9CF5&background=EBF4FF"},"user_info":{"id":2,"firstname":"Ruseel","lastname":"Mercado","middlename":"M.","contact":"34142421","birthdate":"2023-12-05","address":"pneranda","created_at":"2023-12-05T11:26:15.000000Z","updated_at":"2023-12-05T11:26:15.000000Z","full_name":"Ruseel Mercado M."},"document_type":{"id":2,"name":"Certificate of Enrollment","created_at":"2023-12-05T11:26:50.000000Z","updated_at":"2023-12-05T11:26:50.000000Z"}},{"id":6,"ref_id":"6576a0eadc7b6","document_type_id":1,"user_id":12,"user_info_id":2,"path":"6576a0eadc7b6.pdf","pushed":1,"created_at":"2023-12-11T05:40:58.000000Z","updated_at":"2023-12-11T06:36:25.000000Z","user":{"id":12,"name":"BossRussel","email":"mercadojohnrussel00@gmail.com","email_verified_at":null,"two_factor_confirmed_at":null,"current_team_id":null,"profile_photo_path":null,"created_at":"2023-12-11T05:40:07.000000Z","updated_at":"2023-12-11T05:40:07.000000Z","profile_photo_url":"https:\/\/ui-avatars.com\/api\/?name=B&color=7F9CF5&background=EBF4FF"},"user_info":{"id":2,"firstname":"Ruseel","lastname":"Mercado","middlename":"M.","contact":"34142421","birthdate":"2023-12-05","address":"pneranda","created_at":"2023-12-05T11:26:15.000000Z","updated_at":"2023-12-05T11:26:15.000000Z","full_name":"Ruseel Mercado M."},"document_type":{"id":1,"name":"Certificate of Grades","created_at":"2023-12-05T10:11:17.000000Z","updated_at":"2023-12-05T10:11:17.000000Z"}},{"id":7,"ref_id":"6576aaf01f85d","document_type_id":3,"user_id":12,"user_info_id":1,"path":"6576aaf01f85d.pdf","pushed":1,"created_at":"2023-12-11T06:23:44.000000Z","updated_at":"2023-12-11T06:36:25.000000Z","user":{"id":12,"name":"BossRussel","email":"mercadojohnrussel00@gmail.com","email_verified_at":null,"two_factor_confirmed_at":null,"current_team_id":null,"profile_photo_path":null,"created_at":"2023-12-11T05:40:07.000000Z","updated_at":"2023-12-11T05:40:07.000000Z","profile_photo_url":"https:\/\/ui-avatars.com\/api\/?name=B&color=7F9CF5&background=EBF4FF"},"user_info":{"id":1,"firstname":"John","lastname":"Doe","middlename":"N\/A","contact":"093289743874","birthdate":"2023-12-10","address":"poruih wenwjs gg","created_at":"2023-12-05T10:11:02.000000Z","updated_at":"2023-12-05T10:11:02.000000Z","full_name":"John Doe"},"document_type":{"id":3,"name":"Form 137","created_at":"2023-12-11T06:23:32.000000Z","updated_at":"2023-12-11T06:23:32.000000Z"}},{"id":8,"ref_id":"6576ade17ff35","document_type_id":1,"user_id":12,"user_info_id":2,"path":"6576ade17ff35.pdf","pushed":1,"created_at":"2023-12-11T06:36:17.000000Z","updated_at":"2023-12-11T06:36:26.000000Z","user":{"id":12,"name":"BossRussel","email":"mercadojohnrussel00@gmail.com","email_verified_at":null,"two_factor_confirmed_at":null,"current_team_id":null,"profile_photo_path":null,"created_at":"2023-12-11T05:40:07.000000Z","updated_at":"2023-12-11T05:40:07.000000Z","profile_photo_url":"https:\/\/ui-avatars.com\/api\/?name=B&color=7F9CF5&background=EBF4FF"},"user_info":{"id":2,"firstname":"Ruseel","lastname":"Mercado","middlename":"M.","contact":"34142421","birthdate":"2023-12-05","address":"pneranda","created_at":"2023-12-05T11:26:15.000000Z","updated_at":"2023-12-05T11:26:15.000000Z","full_name":"Ruseel Mercado M."},"document_type":{"id":1,"name":"Certificate of Grades","created_at":"2023-12-05T10:11:17.000000Z","updated_at":"2023-12-05T10:11:17.000000Z"}},{"id":9,"ref_id":"6576af43bebfa","document_type_id":3,"user_id":12,"user_info_id":4,"path":"6576af43bebfa.pdf","pushed":0,"created_at":"2023-12-11T06:42:11.000000Z","updated_at":"2023-12-11T06:42:12.000000Z","user":{"id":12,"name":"BossRussel","email":"mercadojohnrussel00@gmail.com","email_verified_at":null,"two_factor_confirmed_at":null,"current_team_id":null,"profile_photo_path":null,"created_at":"2023-12-11T05:40:07.000000Z","updated_at":"2023-12-11T05:40:07.000000Z","profile_photo_url":"https:\/\/ui-avatars.com\/api\/?name=B&color=7F9CF5&background=EBF4FF"},"user_info":{"id":4,"firstname":"Remric","lastname":"Paderes","middlename":"Martin","contact":"09351421213","birthdate":"2023-12-01","address":"sadasdaaw","created_at":"2023-12-11T06:41:42.000000Z","updated_at":"2023-12-11T06:41:42.000000Z","full_name":"Remric Paderes M."},"document_type":{"id":3,"name":"Form 137","created_at":"2023-12-11T06:23:32.000000Z","updated_at":"2023-12-11T06:23:32.000000Z"}},{"id":2,"ref_id":"656ef76a0373e","document_type_id":1,"user_id":11,"user_info_id":1,"path":"656ef76a0373e.pdf","pushed":1,"created_at":"2023-12-05T10:11:54.000000Z","updated_at":"2023-12-11T06:42:29.000000Z","user":{"id":11,"name":"Test User","email":"test@example.com","email_verified_at":"2023-12-05T10:10:27.000000Z","two_factor_confirmed_at":null,"current_team_id":null,"profile_photo_path":null,"created_at":"2023-12-05T10:10:27.000000Z","updated_at":"2023-12-05T10:10:27.000000Z","profile_photo_url":"https:\/\/ui-avatars.com\/api\/?name=T+U&color=7F9CF5&background=EBF4FF"},"user_info":{"id":1,"firstname":"John","lastname":"Doe","middlename":"N\/A","contact":"093289743874","birthdate":"2023-12-10","address":"poruih wenwjs gg","created_at":"2023-12-05T10:11:02.000000Z","updated_at":"2023-12-05T10:11:02.000000Z","full_name":"John Doe"},"document_type":{"id":1,"name":"Certificate of Grades","created_at":"2023-12-05T10:11:17.000000Z","updated_at":"2023-12-05T10:11:17.000000Z"}},{"id":3,"ref_id":"656ef9917c3c5","document_type_id":1,"user_id":11,"user_info_id":1,"path":"656ef9917c3c5.pdf","pushed":1,"created_at":"2023-12-05T10:21:05.000000Z","updated_at":"2023-12-11T06:42:29.000000Z","user":{"id":11,"name":"Test User","email":"test@example.com","email_verified_at":"2023-12-05T10:10:27.000000Z","two_factor_confirmed_at":null,"current_team_id":null,"profile_photo_path":null,"created_at":"2023-12-05T10:10:27.000000Z","updated_at":"2023-12-05T10:10:27.000000Z","profile_photo_url":"https:\/\/ui-avatars.com\/api\/?name=T+U&color=7F9CF5&background=EBF4FF"},"user_info":{"id":1,"firstname":"John","lastname":"Doe","middlename":"N\/A","contact":"093289743874","birthdate":"2023-12-10","address":"poruih wenwjs gg","created_at":"2023-12-05T10:11:02.000000Z","updated_at":"2023-12-05T10:11:02.000000Z","full_name":"John Doe"},"document_type":{"id":1,"name":"Certificate of Grades","created_at":"2023-12-05T10:11:17.000000Z","updated_at":"2023-12-05T10:11:17.000000Z"}},{"id":4,"ref_id":"656f03c288a5b","document_type_id":1,"user_id":11,"user_info_id":1,"path":"656f03c288a5b.pdf","pushed":1,"created_at":"2023-12-05T11:04:34.000000Z","updated_at":"2023-12-11T06:42:29.000000Z","user":{"id":11,"name":"Test User","email":"test@example.com","email_verified_at":"2023-12-05T10:10:27.000000Z","two_factor_confirmed_at":null,"current_team_id":null,"profile_photo_path":null,"created_at":"2023-12-05T10:10:27.000000Z","updated_at":"2023-12-05T10:10:27.000000Z","profile_photo_url":"https:\/\/ui-avatars.com\/api\/?name=T+U&color=7F9CF5&background=EBF4FF"},"user_info":{"id":1,"firstname":"John","lastname":"Doe","middlename":"N\/A","contact":"093289743874","birthdate":"2023-12-10","address":"poruih wenwjs gg","created_at":"2023-12-05T10:11:02.000000Z","updated_at":"2023-12-05T10:11:02.000000Z","full_name":"John Doe"},"document_type":{"id":1,"name":"Certificate of Grades","created_at":"2023-12-05T10:11:17.000000Z","updated_at":"2023-12-05T10:11:17.000000Z"}},{"id":5,"ref_id":"656f091b9aac5","document_type_id":2,"user_id":11,"user_info_id":2,"path":"656f091b9aac5.pdf","pushed":1,"created_at":"2023-12-05T11:27:23.000000Z","updated_at":"2023-12-11T06:42:29.000000Z","user":{"id":11,"name":"Test User","email":"test@example.com","email_verified_at":"2023-12-05T10:10:27.000000Z","two_factor_confirmed_at":null,"current_team_id":null,"profile_photo_path":null,"created_at":"2023-12-05T10:10:27.000000Z","updated_at":"2023-12-05T10:10:27.000000Z","profile_photo_url":"https:\/\/ui-avatars.com\/api\/?name=T+U&color=7F9CF5&background=EBF4FF"},"user_info":{"id":2,"firstname":"Ruseel","lastname":"Mercado","middlename":"M.","contact":"34142421","birthdate":"2023-12-05","address":"pneranda","created_at":"2023-12-05T11:26:15.000000Z","updated_at":"2023-12-05T11:26:15.000000Z","full_name":"Ruseel Mercado M."},"document_type":{"id":2,"name":"Certificate of Enrollment","created_at":"2023-12-05T11:26:50.000000Z","updated_at":"2023-12-05T11:26:50.000000Z"}},{"id":6,"ref_id":"6576a0eadc7b6","document_type_id":1,"user_id":12,"user_info_id":2,"path":"6576a0eadc7b6.pdf","pushed":1,"created_at":"2023-12-11T05:40:58.000000Z","updated_at":"2023-12-11T06:42:30.000000Z","user":{"id":12,"name":"BossRussel","email":"mercadojohnrussel00@gmail.com","email_verified_at":null,"two_factor_confirmed_at":null,"current_team_id":null,"profile_photo_path":null,"created_at":"2023-12-11T05:40:07.000000Z","updated_at":"2023-12-11T05:40:07.000000Z","profile_photo_url":"https:\/\/ui-avatars.com\/api\/?name=B&color=7F9CF5&background=EBF4FF"},"user_info":{"id":2,"firstname":"Ruseel","lastname":"Mercado","middlename":"M.","contact":"34142421","birthdate":"2023-12-05","address":"pneranda","created_at":"2023-12-05T11:26:15.000000Z","updated_at":"2023-12-05T11:26:15.000000Z","full_name":"Ruseel Mercado M."},"document_type":{"id":1,"name":"Certificate of Grades","created_at":"2023-12-05T10:11:17.000000Z","updated_at":"2023-12-05T10:11:17.000000Z"}},{"id":7,"ref_id":"6576aaf01f85d","document_type_id":3,"user_id":12,"user_info_id":1,"path":"6576aaf01f85d.pdf","pushed":1,"created_at":"2023-12-11T06:23:44.000000Z","updated_at":"2023-12-11T06:42:30.000000Z","user":{"id":12,"name":"BossRussel","email":"mercadojohnrussel00@gmail.com","email_verified_at":null,"two_factor_confirmed_at":null,"current_team_id":null,"profile_photo_path":null,"created_at":"2023-12-11T05:40:07.000000Z","updated_at":"2023-12-11T05:40:07.000000Z","profile_photo_url":"https:\/\/ui-avatars.com\/api\/?name=B&color=7F9CF5&background=EBF4FF"},"user_info":{"id":1,"firstname":"John","lastname":"Doe","middlename":"N\/A","contact":"093289743874","birthdate":"2023-12-10","address":"poruih wenwjs gg","created_at":"2023-12-05T10:11:02.000000Z","updated_at":"2023-12-05T10:11:02.000000Z","full_name":"John Doe"},"document_type":{"id":3,"name":"Form 137","created_at":"2023-12-11T06:23:32.000000Z","updated_at":"2023-12-11T06:23:32.000000Z"}},{"id":8,"ref_id":"6576ade17ff35","document_type_id":1,"user_id":12,"user_info_id":2,"path":"6576ade17ff35.pdf","pushed":1,"created_at":"2023-12-11T06:36:17.000000Z","updated_at":"2023-12-11T06:42:30.000000Z","user":{"id":12,"name":"BossRussel","email":"mercadojohnrussel00@gmail.com","email_verified_at":null,"two_factor_confirmed_at":null,"current_team_id":null,"profile_photo_path":null,"created_at":"2023-12-11T05:40:07.000000Z","updated_at":"2023-12-11T05:40:07.000000Z","profile_photo_url":"https:\/\/ui-avatars.com\/api\/?name=B&color=7F9CF5&background=EBF4FF"},"user_info":{"id":2,"firstname":"Ruseel","lastname":"Mercado","middlename":"M.","contact":"34142421","birthdate":"2023-12-05","address":"pneranda","created_at":"2023-12-05T11:26:15.000000Z","updated_at":"2023-12-05T11:26:15.000000Z","full_name":"Ruseel Mercado M."},"document_type":{"id":1,"name":"Certificate of Grades","created_at":"2023-12-05T10:11:17.000000Z","updated_at":"2023-12-05T10:11:17.000000Z"}},{"id":9,"ref_id":"6576af43bebfa","document_type_id":3,"user_id":12,"user_info_id":4,"path":"6576af43bebfa.pdf","pushed":1,"created_at":"2023-12-11T06:42:11.000000Z","updated_at":"2023-12-11T06:42:30.000000Z","user":{"id":12,"name":"BossRussel","email":"mercadojohnrussel00@gmail.com","email_verified_at":null,"two_factor_confirmed_at":null,"current_team_id":null,"profile_photo_path":null,"created_at":"2023-12-11T05:40:07.000000Z","updated_at":"2023-12-11T05:40:07.000000Z","profile_photo_url":"https:\/\/ui-avatars.com\/api\/?name=B&color=7F9CF5&background=EBF4FF"},"user_info":{"id":4,"firstname":"Remric","lastname":"Paderes","middlename":"Martin","contact":"09351421213","birthdate":"2023-12-01","address":"sadasdaaw","created_at":"2023-12-11T06:41:42.000000Z","updated_at":"2023-12-11T06:41:42.000000Z","full_name":"Remric Paderes M."},"document_type":{"id":3,"name":"Form 137","created_at":"2023-12-11T06:23:32.000000Z","updated_at":"2023-12-11T06:23:32.000000Z"}},{"id":10,"ref_id":"6576b1e6b042e","document_type_id":1,"user_id":12,"user_info_id":5,"path":"6576b1e6b042e.pdf","pushed":0,"created_at":"2023-12-11T06:53:26.000000Z","updated_at":"2023-12-11T06:53:28.000000Z","user":{"id":12,"name":"BossRussel","email":"mercadojohnrussel00@gmail.com","email_verified_at":null,"two_factor_confirmed_at":null,"current_team_id":null,"profile_photo_path":null,"created_at":"2023-12-11T05:40:07.000000Z","updated_at":"2023-12-11T05:40:07.000000Z","profile_photo_url":"https:\/\/ui-avatars.com\/api\/?name=B&color=7F9CF5&background=EBF4FF"},"user_info":{"id":5,"firstname":"Daniel","lastname":"Cuevas","middlename":"L.","contact":"09352283232","birthdate":"2023-12-18","address":"efihawjwkbd","created_at":"2023-12-11T06:53:06.000000Z","updated_at":"2023-12-11T06:53:06.000000Z","full_name":"Daniel Cuevas L."},"document_type":{"id":1,"name":"Certificate of Grades","created_at":"2023-12-05T10:11:17.000000Z","updated_at":"2023-12-05T10:11:17.000000Z"}},{"id":2,"ref_id":"656ef76a0373e","document_type_id":1,"user_id":11,"user_info_id":1,"path":"656ef76a0373e.pdf","pushed":1,"created_at":"2023-12-05T10:11:54.000000Z","updated_at":"2023-12-11T06:53:50.000000Z","user":{"id":11,"name":"Test User","email":"test@example.com","email_verified_at":"2023-12-05T10:10:27.000000Z","two_factor_confirmed_at":null,"current_team_id":null,"profile_photo_path":null,"created_at":"2023-12-05T10:10:27.000000Z","updated_at":"2023-12-05T10:10:27.000000Z","profile_photo_url":"https:\/\/ui-avatars.com\/api\/?name=T+U&color=7F9CF5&background=EBF4FF"},"user_info":{"id":1,"firstname":"John","lastname":"Doe","middlename":"N\/A","contact":"093289743874","birthdate":"2023-12-10","address":"poruih wenwjs gg","created_at":"2023-12-05T10:11:02.000000Z","updated_at":"2023-12-05T10:11:02.000000Z","full_name":"John Doe"},"document_type":{"id":1,"name":"Certificate of Grades","created_at":"2023-12-05T10:11:17.000000Z","updated_at":"2023-12-05T10:11:17.000000Z"}},{"id":3,"ref_id":"656ef9917c3c5","document_type_id":1,"user_id":11,"user_info_id":1,"path":"656ef9917c3c5.pdf","pushed":1,"created_at":"2023-12-05T10:21:05.000000Z","updated_at":"2023-12-11T06:53:50.000000Z","user":{"id":11,"name":"Test User","email":"test@example.com","email_verified_at":"2023-12-05T10:10:27.000000Z","two_factor_confirmed_at":null,"current_team_id":null,"profile_photo_path":null,"created_at":"2023-12-05T10:10:27.000000Z","updated_at":"2023-12-05T10:10:27.000000Z","profile_photo_url":"https:\/\/ui-avatars.com\/api\/?name=T+U&color=7F9CF5&background=EBF4FF"},"user_info":{"id":1,"firstname":"John","lastname":"Doe","middlename":"N\/A","contact":"093289743874","birthdate":"2023-12-10","address":"poruih wenwjs gg","created_at":"2023-12-05T10:11:02.000000Z","updated_at":"2023-12-05T10:11:02.000000Z","full_name":"John Doe"},"document_type":{"id":1,"name":"Certificate of Grades","created_at":"2023-12-05T10:11:17.000000Z","updated_at":"2023-12-05T10:11:17.000000Z"}},{"id":4,"ref_id":"656f03c288a5b","document_type_id":1,"user_id":11,"user_info_id":1,"path":"656f03c288a5b.pdf","pushed":1,"created_at":"2023-12-05T11:04:34.000000Z","updated_at":"2023-12-11T06:53:50.000000Z","user":{"id":11,"name":"Test User","email":"test@example.com","email_verified_at":"2023-12-05T10:10:27.000000Z","two_factor_confirmed_at":null,"current_team_id":null,"profile_photo_path":null,"created_at":"2023-12-05T10:10:27.000000Z","updated_at":"2023-12-05T10:10:27.000000Z","profile_photo_url":"https:\/\/ui-avatars.com\/api\/?name=T+U&color=7F9CF5&background=EBF4FF"},"user_info":{"id":1,"firstname":"John","lastname":"Doe","middlename":"N\/A","contact":"093289743874","birthdate":"2023-12-10","address":"poruih wenwjs gg","created_at":"2023-12-05T10:11:02.000000Z","updated_at":"2023-12-05T10:11:02.000000Z","full_name":"John Doe"},"document_type":{"id":1,"name":"Certificate of Grades","created_at":"2023-12-05T10:11:17.000000Z","updated_at":"2023-12-05T10:11:17.000000Z"}},{"id":5,"ref_id":"656f091b9aac5","document_type_id":2,"user_id":11,"user_info_id":2,"path":"656f091b9aac5.pdf","pushed":1,"created_at":"2023-12-05T11:27:23.000000Z","updated_at":"2023-12-11T06:53:50.000000Z","user":{"id":11,"name":"Test User","email":"test@example.com","email_verified_at":"2023-12-05T10:10:27.000000Z","two_factor_confirmed_at":null,"current_team_id":null,"profile_photo_path":null,"created_at":"2023-12-05T10:10:27.000000Z","updated_at":"2023-12-05T10:10:27.000000Z","profile_photo_url":"https:\/\/ui-avatars.com\/api\/?name=T+U&color=7F9CF5&background=EBF4FF"},"user_info":{"id":2,"firstname":"Ruseel","lastname":"Mercado","middlename":"M.","contact":"34142421","birthdate":"2023-12-05","address":"pneranda","created_at":"2023-12-05T11:26:15.000000Z","updated_at":"2023-12-05T11:26:15.000000Z","full_name":"Ruseel Mercado M."},"document_type":{"id":2,"name":"Certificate of Enrollment","created_at":"2023-12-05T11:26:50.000000Z","updated_at":"2023-12-05T11:26:50.000000Z"}},{"id":6,"ref_id":"6576a0eadc7b6","document_type_id":1,"user_id":12,"user_info_id":2,"path":"6576a0eadc7b6.pdf","pushed":1,"created_at":"2023-12-11T05:40:58.000000Z","updated_at":"2023-12-11T06:53:51.000000Z","user":{"id":12,"name":"BossRussel","email":"mercadojohnrussel00@gmail.com","email_verified_at":null,"two_factor_confirmed_at":null,"current_team_id":null,"profile_photo_path":null,"created_at":"2023-12-11T05:40:07.000000Z","updated_at":"2023-12-11T05:40:07.000000Z","profile_photo_url":"https:\/\/ui-avatars.com\/api\/?name=B&color=7F9CF5&background=EBF4FF"},"user_info":{"id":2,"firstname":"Ruseel","lastname":"Mercado","middlename":"M.","contact":"34142421","birthdate":"2023-12-05","address":"pneranda","created_at":"2023-12-05T11:26:15.000000Z","updated_at":"2023-12-05T11:26:15.000000Z","full_name":"Ruseel Mercado M."},"document_type":{"id":1,"name":"Certificate of Grades","created_at":"2023-12-05T10:11:17.000000Z","updated_at":"2023-12-05T10:11:17.000000Z"}},{"id":7,"ref_id":"6576aaf01f85d","document_type_id":3,"user_id":12,"user_info_id":1,"path":"6576aaf01f85d.pdf","pushed":1,"created_at":"2023-12-11T06:23:44.000000Z","updated_at":"2023-12-11T06:53:51.000000Z","user":{"id":12,"name":"BossRussel","email":"mercadojohnrussel00@gmail.com","email_verified_at":null,"two_factor_confirmed_at":null,"current_team_id":null,"profile_photo_path":null,"created_at":"2023-12-11T05:40:07.000000Z","updated_at":"2023-12-11T05:40:07.000000Z","profile_photo_url":"https:\/\/ui-avatars.com\/api\/?name=B&color=7F9CF5&background=EBF4FF"},"user_info":{"id":1,"firstname":"John","lastname":"Doe","middlename":"N\/A","contact":"093289743874","birthdate":"2023-12-10","address":"poruih wenwjs gg","created_at":"2023-12-05T10:11:02.000000Z","updated_at":"2023-12-05T10:11:02.000000Z","full_name":"John Doe"},"document_type":{"id":3,"name":"Form 137","created_at":"2023-12-11T06:23:32.000000Z","updated_at":"2023-12-11T06:23:32.000000Z"}},{"id":8,"ref_id":"6576ade17ff35","document_type_id":1,"user_id":12,"user_info_id":2,"path":"6576ade17ff35.pdf","pushed":1,"created_at":"2023-12-11T06:36:17.000000Z","updated_at":"2023-12-11T06:53:51.000000Z","user":{"id":12,"name":"BossRussel","email":"mercadojohnrussel00@gmail.com","email_verified_at":null,"two_factor_confirmed_at":null,"current_team_id":null,"profile_photo_path":null,"created_at":"2023-12-11T05:40:07.000000Z","updated_at":"2023-12-11T05:40:07.000000Z","profile_photo_url":"https:\/\/ui-avatars.com\/api\/?name=B&color=7F9CF5&background=EBF4FF"},"user_info":{"id":2,"firstname":"Ruseel","lastname":"Mercado","middlename":"M.","contact":"34142421","birthdate":"2023-12-05","address":"pneranda","created_at":"2023-12-05T11:26:15.000000Z","updated_at":"2023-12-05T11:26:15.000000Z","full_name":"Ruseel Mercado M."},"document_type":{"id":1,"name":"Certificate of Grades","created_at":"2023-12-05T10:11:17.000000Z","updated_at":"2023-12-05T10:11:17.000000Z"}},{"id":9,"ref_id":"6576af43bebfa","document_type_id":3,"user_id":12,"user_info_id":4,"path":"6576af43bebfa.pdf","pushed":1,"created_at":"2023-12-11T06:42:11.000000Z","updated_at":"2023-12-11T06:53:51.000000Z","user":{"id":12,"name":"BossRussel","email":"mercadojohnrussel00@gmail.com","email_verified_at":null,"two_factor_confirmed_at":null,"current_team_id":null,"profile_photo_path":null,"created_at":"2023-12-11T05:40:07.000000Z","updated_at":"2023-12-11T05:40:07.000000Z","profile_photo_url":"https:\/\/ui-avatars.com\/api\/?name=B&color=7F9CF5&background=EBF4FF"},"user_info":{"id":4,"firstname":"Remric","lastname":"Paderes","middlename":"Martin","contact":"09351421213","birthdate":"2023-12-01","address":"sadasdaaw","created_at":"2023-12-11T06:41:42.000000Z","updated_at":"2023-12-11T06:41:42.000000Z","full_name":"Remric Paderes M."},"document_type":{"id":3,"name":"Form 137","created_at":"2023-12-11T06:23:32.000000Z","updated_at":"2023-12-11T06:23:32.000000Z"}},{"id":10,"ref_id":"6576b1e6b042e","document_type_id":1,"user_id":12,"user_info_id":5,"path":"6576b1e6b042e.pdf","pushed":1,"created_at":"2023-12-11T06:53:26.000000Z","updated_at":"2023-12-11T06:53:51.000000Z","user":{"id":12,"name":"BossRussel","email":"mercadojohnrussel00@gmail.com","email_verified_at":null,"two_factor_confirmed_at":null,"current_team_id":null,"profile_photo_path":null,"created_at":"2023-12-11T05:40:07.000000Z","updated_at":"2023-12-11T05:40:07.000000Z","profile_photo_url":"https:\/\/ui-avatars.com\/api\/?name=B&color=7F9CF5&background=EBF4FF"},"user_info":{"id":5,"firstname":"Daniel","lastname":"Cuevas","middlename":"L.","contact":"09352283232","birthdate":"2023-12-18","address":"efihawjwkbd","created_at":"2023-12-11T06:53:06.000000Z","updated_at":"2023-12-11T06:53:06.000000Z","full_name":"Daniel Cuevas L."},"document_type":{"id":1,"name":"Certificate of Grades","created_at":"2023-12-05T10:11:17.000000Z","updated_at":"2023-12-05T10:11:17.000000Z"}},{"id":11,"ref_id":"65782979a6692","document_type_id":1,"user_id":12,"user_info_id":1,"path":"65782979a6692.pdf","pushed":0,"created_at":"2023-12-12T09:35:53.000000Z","updated_at":"2023-12-12T09:35:57.000000Z","user":{"id":12,"name":"BossRussel","email":"mercadojohnrussel00@gmail.com","email_verified_at":null,"two_factor_confirmed_at":null,"current_team_id":null,"profile_photo_path":null,"created_at":"2023-12-11T05:40:07.000000Z","updated_at":"2023-12-11T05:40:07.000000Z","profile_photo_url":"https:\/\/ui-avatars.com\/api\/?name=B&color=7F9CF5&background=EBF4FF"},"user_info":{"id":1,"firstname":"John","lastname":"Doe","middlename":"N\/A","contact":"093289743874","birthdate":"2023-12-10","address":"poruih wenwjs gg","created_at":"2023-12-05T10:11:02.000000Z","updated_at":"2023-12-05T10:11:02.000000Z","full_name":"John Doe"},"document_type":{"id":1,"name":"Certificate of Grades","created_at":"2023-12-05T10:11:17.000000Z","updated_at":"2023-12-05T10:11:17.000000Z"}},{"id":1,"ref_id":"6578491f347c6","document_type_id":1,"user_id":12,"user_info_id":1,"path":"6578491f347c6.pdf","pushed":0,"created_at":"2023-12-12T11:50:55.000000Z","updated_at":"2023-12-12T11:50:56.000000Z","user":{"id":12,"name":"Jericho Abesamis","email":"abesamisjericho71@gmail.com","email_verified_at":null,"two_factor_confirmed_at":null,"current_team_id":null,"profile_photo_path":null,"created_at":"2023-12-12T11:49:37.000000Z","updated_at":"2023-12-12T11:49:37.000000Z","profile_photo_url":"https:\/\/ui-avatars.com\/api\/?name=J+A&color=7F9CF5&background=EBF4FF"},"user_info":{"id":1,"firstname":"Daniel","lastname":"Cuevas","middlename":"L","contact":"231231311231","birthdate":"2023-12-03","address":"awdawdhawhdawui","created_at":"2023-12-12T11:50:25.000000Z","updated_at":"2023-12-12T11:50:25.000000Z","full_name":"Daniel Cuevas L."},"document_type":{"id":1,"name":"Form 137","created_at":"2023-12-12T11:50:41.000000Z","updated_at":"2023-12-12T11:50:41.000000Z"}},{"id":1,"ref_id":"6578491f347c6","document_type_id":1,"user_id":12,"user_info_id":1,"path":"6578491f347c6.pdf","pushed":1,"created_at":"2023-12-12T11:50:55.000000Z","updated_at":"2023-12-12T11:51:07.000000Z","user":{"id":12,"name":"Jericho Abesamis","email":"abesamisjericho71@gmail.com","email_verified_at":null,"two_factor_confirmed_at":null,"current_team_id":null,"profile_photo_path":null,"created_at":"2023-12-12T11:49:37.000000Z","updated_at":"2023-12-12T11:49:37.000000Z","profile_photo_url":"https:\/\/ui-avatars.com\/api\/?name=J+A&color=7F9CF5&background=EBF4FF"},"user_info":{"id":1,"firstname":"Daniel","lastname":"Cuevas","middlename":"L","contact":"231231311231","birthdate":"2023-12-03","address":"awdawdhawhdawui","created_at":"2023-12-12T11:50:25.000000Z","updated_at":"2023-12-12T11:50:25.000000Z","full_name":"Daniel Cuevas L."},"document_type":{"id":1,"name":"Form 137","created_at":"2023-12-12T11:50:41.000000Z","updated_at":"2023-12-12T11:50:41.000000Z"}},{"id":1,"ref_id":"6578491f347c6","document_type_id":1,"user_id":12,"user_info_id":1,"path":"6578491f347c6.pdf","pushed":1,"created_at":"2023-12-12T11:50:55.000000Z","updated_at":"2023-12-12T11:51:21.000000Z","user":{"id":12,"name":"Jericho Abesamis","email":"abesamisjericho71@gmail.com","email_verified_at":null,"two_factor_confirmed_at":null,"current_team_id":null,"profile_photo_path":null,"created_at":"2023-12-12T11:49:37.000000Z","updated_at":"2023-12-12T11:49:37.000000Z","profile_photo_url":"https:\/\/ui-avatars.com\/api\/?name=J+A&color=7F9CF5&background=EBF4FF"},"user_info":{"id":1,"firstname":"Daniel","lastname":"Cuevas","middlename":"L","contact":"231231311231","birthdate":"2023-12-03","address":"awdawdhawhdawui","created_at":"2023-12-12T11:50:25.000000Z","updated_at":"2023-12-12T11:50:25.000000Z","full_name":"Daniel Cuevas L."},"document_type":{"id":1,"name":"Form 137","created_at":"2023-12-12T11:50:41.000000Z","updated_at":"2023-12-12T11:50:41.000000Z"}},{"id":1,"ref_id":"6578491f347c6","document_type_id":1,"user_id":12,"user_info_id":1,"path":"6578491f347c6.pdf","pushed":1,"created_at":"2023-12-12T11:50:55.000000Z","updated_at":"2023-12-12T11:51:58.000000Z","user":{"id":12,"name":"Jericho Abesamis","email":"abesamisjericho71@gmail.com","email_verified_at":null,"two_factor_confirmed_at":null,"current_team_id":null,"profile_photo_path":null,"created_at":"2023-12-12T11:49:37.000000Z","updated_at":"2023-12-12T11:49:37.000000Z","profile_photo_url":"https:\/\/ui-avatars.com\/api\/?name=J+A&color=7F9CF5&background=EBF4FF"},"user_info":{"id":1,"firstname":"Daniel","lastname":"Cuevas","middlename":"L","contact":"231231311231","birthdate":"2023-12-03","address":"awdawdhawhdawui","created_at":"2023-12-12T11:50:25.000000Z","updated_at":"2023-12-12T11:50:25.000000Z","full_name":"Daniel Cuevas L."},"document_type":{"id":1,"name":"Form 137","created_at":"2023-12-12T11:50:41.000000Z","updated_at":"2023-12-12T11:50:41.000000Z"}},{"id":1,"ref_id":"6578491f347c6","document_type_id":1,"user_id":12,"user_info_id":1,"path":"6578491f347c6.pdf","pushed":1,"created_at":"2023-12-12T11:50:55.000000Z","updated_at":"2023-12-12T11:53:16.000000Z","user":{"id":12,"name":"Jericho Abesamis","email":"abesamisjericho71@gmail.com","email_verified_at":null,"two_factor_confirmed_at":null,"current_team_id":null,"profile_photo_path":null,"created_at":"2023-12-12T11:49:37.000000Z","updated_at":"2023-12-12T11:49:37.000000Z","profile_photo_url":"https:\/\/ui-avatars.com\/api\/?name=J+A&color=7F9CF5&background=EBF4FF"},"user_info":{"id":1,"firstname":"Daniel","lastname":"Cuevas","middlename":"L","contact":"231231311231","birthdate":"2023-12-03","address":"awdawdhawhdawui","created_at":"2023-12-12T11:50:25.000000Z","updated_at":"2023-12-12T11:50:25.000000Z","full_name":"Daniel Cuevas L."},"document_type":{"id":1,"name":"Form 137","created_at":"2023-12-12T11:50:41.000000Z","updated_at":"2023-12-12T11:50:41.000000Z"}},{"id":1,"ref_id":"6578491f347c6","document_type_id":1,"user_id":12,"user_info_id":1,"path":"6578491f347c6.pdf","pushed":1,"created_at":"2023-12-12T11:50:55.000000Z","updated_at":"2023-12-12T11:53:20.000000Z","user":{"id":12,"name":"Jericho Abesamis","email":"abesamisjericho71@gmail.com","email_verified_at":null,"two_factor_confirmed_at":null,"current_team_id":null,"profile_photo_path":null,"created_at":"2023-12-12T11:49:37.000000Z","updated_at":"2023-12-12T11:49:37.000000Z","profile_photo_url":"https:\/\/ui-avatars.com\/api\/?name=J+A&color=7F9CF5&background=EBF4FF"},"user_info":{"id":1,"firstname":"Daniel","lastname":"Cuevas","middlename":"L","contact":"231231311231","birthdate":"2023-12-03","address":"awdawdhawhdawui","created_at":"2023-12-12T11:50:25.000000Z","updated_at":"2023-12-12T11:50:25.000000Z","full_name":"Daniel Cuevas L."},"document_type":{"id":1,"name":"Form 137","created_at":"2023-12-12T11:50:41.000000Z","updated_at":"2023-12-12T11:50:41.000000Z"}},{"id":1,"ref_id":"6578491f347c6","document_type_id":1,"user_id":12,"user_info_id":1,"path":"6578491f347c6.pdf","pushed":1,"created_at":"2023-12-12T11:50:55.000000Z","updated_at":"2023-12-12T11:53:23.000000Z","user":{"id":12,"name":"Jericho Abesamis","email":"abesamisjericho71@gmail.com","email_verified_at":null,"two_factor_confirmed_at":null,"current_team_id":null,"profile_photo_path":null,"created_at":"2023-12-12T11:49:37.000000Z","updated_at":"2023-12-12T11:49:37.000000Z","profile_photo_url":"https:\/\/ui-avatars.com\/api\/?name=J+A&color=7F9CF5&background=EBF4FF"},"user_info":{"id":1,"firstname":"Daniel","lastname":"Cuevas","middlename":"L","contact":"231231311231","birthdate":"2023-12-03","address":"awdawdhawhdawui","created_at":"2023-12-12T11:50:25.000000Z","updated_at":"2023-12-12T11:50:25.000000Z","full_name":"Daniel Cuevas L."},"document_type":{"id":1,"name":"Form 137","created_at":"2023-12-12T11:50:41.000000Z","updated_at":"2023-12-12T11:50:41.000000Z"}},{"id":1,"ref_id":"6578491f347c6","document_type_id":1,"user_id":12,"user_info_id":1,"path":"6578491f347c6.pdf","pushed":1,"created_at":"2023-12-12T11:50:55.000000Z","updated_at":"2023-12-12T11:53:25.000000Z","user":{"id":12,"name":"Jericho Abesamis","email":"abesamisjericho71@gmail.com","email_verified_at":null,"two_factor_confirmed_at":null,"current_team_id":null,"profile_photo_path":null,"created_at":"2023-12-12T11:49:37.000000Z","updated_at":"2023-12-12T11:49:37.000000Z","profile_photo_url":"https:\/\/ui-avatars.com\/api\/?name=J+A&color=7F9CF5&background=EBF4FF"},"user_info":{"id":1,"firstname":"Daniel","lastname":"Cuevas","middlename":"L","contact":"231231311231","birthdate":"2023-12-03","address":"awdawdhawhdawui","created_at":"2023-12-12T11:50:25.000000Z","updated_at":"2023-12-12T11:50:25.000000Z","full_name":"Daniel Cuevas L."},"document_type":{"id":1,"name":"Form 137","created_at":"2023-12-12T11:50:41.000000Z","updated_at":"2023-12-12T11:50:41.000000Z"}},{"id":1,"ref_id":"6578491f347c6","document_type_id":1,"user_id":12,"user_info_id":1,"path":"6578491f347c6.pdf","pushed":1,"created_at":"2023-12-12T11:50:55.000000Z","updated_at":"2023-12-12T11:53:28.000000Z","user":{"id":12,"name":"Jericho Abesamis","email":"abesamisjericho71@gmail.com","email_verified_at":null,"two_factor_confirmed_at":null,"current_team_id":null,"profile_photo_path":null,"created_at":"2023-12-12T11:49:37.000000Z","updated_at":"2023-12-12T11:49:37.000000Z","profile_photo_url":"https:\/\/ui-avatars.com\/api\/?name=J+A&color=7F9CF5&background=EBF4FF"},"user_info":{"id":1,"firstname":"Daniel","lastname":"Cuevas","middlename":"L","contact":"231231311231","birthdate":"2023-12-03","address":"awdawdhawhdawui","created_at":"2023-12-12T11:50:25.000000Z","updated_at":"2023-12-12T11:50:25.000000Z","full_name":"Daniel Cuevas L."},"document_type":{"id":1,"name":"Form 137","created_at":"2023-12-12T11:50:41.000000Z","updated_at":"2023-12-12T11:50:41.000000Z"}},{"id":1,"ref_id":"6578491f347c6","document_type_id":1,"user_id":12,"user_info_id":1,"path":"6578491f347c6.pdf","pushed":1,"created_at":"2023-12-12T11:50:55.000000Z","updated_at":"2023-12-12T11:53:31.000000Z","user":{"id":12,"name":"Jericho Abesamis","email":"abesamisjericho71@gmail.com","email_verified_at":null,"two_factor_confirmed_at":null,"current_team_id":null,"profile_photo_path":null,"created_at":"2023-12-12T11:49:37.000000Z","updated_at":"2023-12-12T11:49:37.000000Z","profile_photo_url":"https:\/\/ui-avatars.com\/api\/?name=J+A&color=7F9CF5&background=EBF4FF"},"user_info":{"id":1,"firstname":"Daniel","lastname":"Cuevas","middlename":"L","contact":"231231311231","birthdate":"2023-12-03","address":"awdawdhawhdawui","created_at":"2023-12-12T11:50:25.000000Z","updated_at":"2023-12-12T11:50:25.000000Z","full_name":"Daniel Cuevas L."},"document_type":{"id":1,"name":"Form 137","created_at":"2023-12-12T11:50:41.000000Z","updated_at":"2023-12-12T11:50:41.000000Z"}},{"id":1,"ref_id":"6578491f347c6","document_type_id":1,"user_id":12,"user_info_id":1,"path":"6578491f347c6.pdf","pushed":1,"created_at":"2023-12-12T11:50:55.000000Z","updated_at":"2023-12-12T11:53:34.000000Z","user":{"id":12,"name":"Jericho Abesamis","email":"abesamisjericho71@gmail.com","email_verified_at":null,"two_factor_confirmed_at":null,"current_team_id":null,"profile_photo_path":null,"created_at":"2023-12-12T11:49:37.000000Z","updated_at":"2023-12-12T11:49:37.000000Z","profile_photo_url":"https:\/\/ui-avatars.com\/api\/?name=J+A&color=7F9CF5&background=EBF4FF"},"user_info":{"id":1,"firstname":"Daniel","lastname":"Cuevas","middlename":"L","contact":"231231311231","birthdate":"2023-12-03","address":"awdawdhawhdawui","created_at":"2023-12-12T11:50:25.000000Z","updated_at":"2023-12-12T11:50:25.000000Z","full_name":"Daniel Cuevas L."},"document_type":{"id":1,"name":"Form 137","created_at":"2023-12-12T11:50:41.000000Z","updated_at":"2023-12-12T11:50:41.000000Z"}},{"id":1,"ref_id":"6578491f347c6","document_type_id":1,"user_id":12,"user_info_id":1,"path":"6578491f347c6.pdf","pushed":1,"created_at":"2023-12-12T11:50:55.000000Z","updated_at":"2023-12-12T11:53:36.000000Z","user":{"id":12,"name":"Jericho Abesamis","email":"abesamisjericho71@gmail.com","email_verified_at":null,"two_factor_confirmed_at":null,"current_team_id":null,"profile_photo_path":null,"created_at":"2023-12-12T11:49:37.000000Z","updated_at":"2023-12-12T11:49:37.000000Z","profile_photo_url":"https:\/\/ui-avatars.com\/api\/?name=J+A&color=7F9CF5&background=EBF4FF"},"user_info":{"id":1,"firstname":"Daniel","lastname":"Cuevas","middlename":"L","contact":"231231311231","birthdate":"2023-12-03","address":"awdawdhawhdawui","created_at":"2023-12-12T11:50:25.000000Z","updated_at":"2023-12-12T11:50:25.000000Z","full_name":"Daniel Cuevas L."},"document_type":{"id":1,"name":"Form 137","created_at":"2023-12-12T11:50:41.000000Z","updated_at":"2023-12-12T11:50:41.000000Z"}},{"id":1,"ref_id":"6578491f347c6","document_type_id":1,"user_id":12,"user_info_id":1,"path":"6578491f347c6.pdf","pushed":1,"created_at":"2023-12-12T11:50:55.000000Z","updated_at":"2023-12-12T11:53:39.000000Z","user":{"id":12,"name":"Jericho Abesamis","email":"abesamisjericho71@gmail.com","email_verified_at":null,"two_factor_confirmed_at":null,"current_team_id":null,"profile_photo_path":null,"created_at":"2023-12-12T11:49:37.000000Z","updated_at":"2023-12-12T11:49:37.000000Z","profile_photo_url":"https:\/\/ui-avatars.com\/api\/?name=J+A&color=7F9CF5&background=EBF4FF"},"user_info":{"id":1,"firstname":"Daniel","lastname":"Cuevas","middlename":"L","contact":"231231311231","birthdate":"2023-12-03","address":"awdawdhawhdawui","created_at":"2023-12-12T11:50:25.000000Z","updated_at":"2023-12-12T11:50:25.000000Z","full_name":"Daniel Cuevas L."},"document_type":{"id":1,"name":"Form 137","created_at":"2023-12-12T11:50:41.000000Z","updated_at":"2023-12-12T11:50:41.000000Z"}},{"id":1,"ref_id":"6578491f347c6","document_type_id":1,"user_id":12,"user_info_id":1,"path":"6578491f347c6.pdf","pushed":1,"created_at":"2023-12-12T11:50:55.000000Z","updated_at":"2023-12-12T11:53:43.000000Z","user":{"id":12,"name":"Jericho Abesamis","email":"abesamisjericho71@gmail.com","email_verified_at":null,"two_factor_confirmed_at":null,"current_team_id":null,"profile_photo_path":null,"created_at":"2023-12-12T11:49:37.000000Z","updated_at":"2023-12-12T11:49:37.000000Z","profile_photo_url":"https:\/\/ui-avatars.com\/api\/?name=J+A&color=7F9CF5&background=EBF4FF"},"user_info":{"id":1,"firstname":"Daniel","lastname":"Cuevas","middlename":"L","contact":"231231311231","birthdate":"2023-12-03","address":"awdawdhawhdawui","created_at":"2023-12-12T11:50:25.000000Z","updated_at":"2023-12-12T11:50:25.000000Z","full_name":"Daniel Cuevas L."},"document_type":{"id":1,"name":"Form 137","created_at":"2023-12-12T11:50:41.000000Z","updated_at":"2023-12-12T11:50:41.000000Z"}},{"id":1,"ref_id":"6578491f347c6","document_type_id":1,"user_id":12,"user_info_id":1,"path":"6578491f347c6.pdf","pushed":1,"created_at":"2023-12-12T11:50:55.000000Z","updated_at":"2023-12-12T11:53:47.000000Z","user":{"id":12,"name":"Jericho Abesamis","email":"abesamisjericho71@gmail.com","email_verified_at":null,"two_factor_confirmed_at":null,"current_team_id":null,"profile_photo_path":null,"created_at":"2023-12-12T11:49:37.000000Z","updated_at":"2023-12-12T11:49:37.000000Z","profile_photo_url":"https:\/\/ui-avatars.com\/api\/?name=J+A&color=7F9CF5&background=EBF4FF"},"user_info":{"id":1,"firstname":"Daniel","lastname":"Cuevas","middlename":"L","contact":"231231311231","birthdate":"2023-12-03","address":"awdawdhawhdawui","created_at":"2023-12-12T11:50:25.000000Z","updated_at":"2023-12-12T11:50:25.000000Z","full_name":"Daniel Cuevas L."},"document_type":{"id":1,"name":"Form 137","created_at":"2023-12-12T11:50:41.000000Z","updated_at":"2023-12-12T11:50:41.000000Z"}},{"id":1,"ref_id":"6578491f347c6","document_type_id":1,"user_id":12,"user_info_id":1,"path":"6578491f347c6.pdf","pushed":1,"created_at":"2023-12-12T11:50:55.000000Z","updated_at":"2023-12-12T11:53:50.000000Z","user":{"id":12,"name":"Jericho Abesamis","email":"abesamisjericho71@gmail.com","email_verified_at":null,"two_factor_confirmed_at":null,"current_team_id":null,"profile_photo_path":null,"created_at":"2023-12-12T11:49:37.000000Z","updated_at":"2023-12-12T11:49:37.000000Z","profile_photo_url":"https:\/\/ui-avatars.com\/api\/?name=J+A&color=7F9CF5&background=EBF4FF"},"user_info":{"id":1,"firstname":"Daniel","lastname":"Cuevas","middlename":"L","contact":"231231311231","birthdate":"2023-12-03","address":"awdawdhawhdawui","created_at":"2023-12-12T11:50:25.000000Z","updated_at":"2023-12-12T11:50:25.000000Z","full_name":"Daniel Cuevas L."},"document_type":{"id":1,"name":"Form 137","created_at":"2023-12-12T11:50:41.000000Z","updated_at":"2023-12-12T11:50:41.000000Z"}},{"id":1,"ref_id":"6578491f347c6","document_type_id":1,"user_id":12,"user_info_id":1,"path":"6578491f347c6.pdf","pushed":1,"created_at":"2023-12-12T11:50:55.000000Z","updated_at":"2023-12-12T11:53:53.000000Z","user":{"id":12,"name":"Jericho Abesamis","email":"abesamisjericho71@gmail.com","email_verified_at":null,"two_factor_confirmed_at":null,"current_team_id":null,"profile_photo_path":null,"created_at":"2023-12-12T11:49:37.000000Z","updated_at":"2023-12-15T06:51:19.000000Z","profile_photo_url":"https:\/\/ui-avatars.com\/api\/?name=J+A&color=7F9CF5&background=EBF4FF"},"user_info":{"id":1,"firstname":"Daniel","lastname":"Cuevas","middlename":"L","contact":"231231311231","birthdate":"2023-12-03","address":"awdawdhawhdawui","created_at":"2023-12-12T11:50:25.000000Z","updated_at":"2023-12-12T11:50:25.000000Z","full_name":"Daniel Cuevas L."},"document_type":{"id":1,"name":"Form 137","created_at":"2023-12-12T11:50:41.000000Z","updated_at":"2023-12-12T11:50:41.000000Z"}},{"id":2,"ref_id":"657bf85a09138","document_type_id":2,"user_id":12,"user_info_id":2,"path":"657bf85a09138.pdf","pushed":0,"created_at":"2023-12-15T06:55:22.000000Z","updated_at":"2023-12-15T06:55:24.000000Z","user":{"id":12,"name":"Jericho Abesamis","email":"abesamisjericho71@gmail.com","email_verified_at":null,"two_factor_confirmed_at":null,"current_team_id":null,"profile_photo_path":null,"created_at":"2023-12-12T11:49:37.000000Z","updated_at":"2023-12-15T06:51:19.000000Z","profile_photo_url":"https:\/\/ui-avatars.com\/api\/?name=J+A&color=7F9CF5&background=EBF4FF"},"user_info":{"id":2,"firstname":"Francis Jonil","lastname":"Mabalay","middlename":"z","contact":"0935321321","birthdate":"2023-12-06","address":"adawaewea","created_at":"2023-12-15T06:54:26.000000Z","updated_at":"2023-12-15T06:54:26.000000Z","full_name":"Francis Jonil Mabalay Z."},"document_type":{"id":2,"name":"Certificate of Grades","created_at":"2023-12-15T06:55:02.000000Z","updated_at":"2023-12-15T06:55:02.000000Z"}},{"id":1,"ref_id":"657c02d7c6181","document_type_id":1,"user_id":11,"user_info_id":1,"path":"657c02d7c6181.pdf","pushed":0,"created_at":"2023-12-15T07:40:07.000000Z","updated_at":"2023-12-15T07:40:56.000000Z","user":{"id":11,"name":"Test User","email":"test@example.com","email_verified_at":"2023-12-15T07:37:53.000000Z","two_factor_confirmed_at":null,"current_team_id":null,"profile_photo_path":null,"created_at":"2023-12-15T07:37:53.000000Z","updated_at":"2023-12-15T07:37:53.000000Z","profile_photo_url":"https:\/\/ui-avatars.com\/api\/?name=T+U&color=7F9CF5&background=EBF4FF"},"user_info":{"id":1,"firstname":"Jane","lastname":"Doe","middlename":"N\/A","contact":"4223423423","birthdate":"2023-12-12","address":"234234234","created_at":"2023-12-15T07:39:41.000000Z","updated_at":"2023-12-15T07:39:41.000000Z","full_name":"Jane Doe"},"document_type":{"id":1,"name":"COE","created_at":"2023-12-15T07:39:54.000000Z","updated_at":"2023-12-15T07:39:54.000000Z"}},{"id":1,"ref_id":"657c02d7c6181","document_type_id":1,"user_id":11,"user_info_id":1,"path":"657c02d7c6181.pdf","pushed":1,"created_at":"2023-12-15T07:40:07.000000Z","updated_at":"2023-12-15T07:41:11.000000Z","user":{"id":11,"name":"Test User","email":"test@example.com","email_verified_at":"2023-12-15T07:37:53.000000Z","two_factor_confirmed_at":null,"current_team_id":null,"profile_photo_path":null,"created_at":"2023-12-15T07:37:53.000000Z","updated_at":"2023-12-15T07:37:53.000000Z","profile_photo_url":"https:\/\/ui-avatars.com\/api\/?name=T+U&color=7F9CF5&background=EBF4FF"},"user_info":{"id":1,"firstname":"Jane","lastname":"Doe","middlename":"N\/A","contact":"4223423423","birthdate":"2023-12-12","address":"234234234","created_at":"2023-12-15T07:39:41.000000Z","updated_at":"2023-12-15T07:39:41.000000Z","full_name":"Jane Doe"},"document_type":{"id":1,"name":"COE","created_at":"2023-12-15T07:39:54.000000Z","updated_at":"2023-12-15T07:39:54.000000Z"}},{"id":1,"ref_id":"657c02d7c6181","document_type_id":1,"user_id":11,"user_info_id":1,"path":"657c02d7c6181.pdf","pushed":1,"created_at":"2023-12-15T07:40:07.000000Z","updated_at":"2023-12-15T07:46:11.000000Z","user":{"id":11,"name":"Test User","email":"test@example.com","email_verified_at":"2023-12-15T07:37:53.000000Z","two_factor_confirmed_at":null,"current_team_id":null,"profile_photo_path":null,"created_at":"2023-12-15T07:37:53.000000Z","updated_at":"2023-12-15T07:37:53.000000Z","profile_photo_url":"https:\/\/ui-avatars.com\/api\/?name=T+U&color=7F9CF5&background=EBF4FF"},"user_info":{"id":1,"firstname":"Jane","lastname":"Doe","middlename":"N\/A","contact":"4223423423","birthdate":"2023-12-12","address":"234234234","created_at":"2023-12-15T07:39:41.000000Z","updated_at":"2023-12-15T07:39:41.000000Z","full_name":"Jane Doe"},"document_type":{"id":1,"name":"COE","created_at":"2023-12-15T07:39:54.000000Z","updated_at":"2023-12-15T07:39:54.000000Z"}},{"id":2,"ref_id":"657d59ba94698","document_type_id":2,"user_id":12,"user_info_id":2,"path":"657d59ba94698.pdf","pushed":0,"created_at":"2023-12-16T08:03:06.000000Z","updated_at":"2023-12-16T08:03:08.000000Z","user":{"id":12,"name":"Daniel Cuevas","email":"cuevas@gmail.com","email_verified_at":null,"two_factor_confirmed_at":null,"current_team_id":null,"profile_photo_path":null,"created_at":"2023-12-16T07:59:56.000000Z","updated_at":"2023-12-16T07:59:56.000000Z","profile_photo_url":"https:\/\/ui-avatars.com\/api\/?name=D+C&color=7F9CF5&background=EBF4FF"},"user_info":{"id":2,"firstname":"Paulo","lastname":"Mabutol","middlename":"A","contact":"ghfhgfhgftyryt","birthdate":"2023-12-01","address":"gjyjygyjjhgyh","created_at":"2023-12-16T08:01:59.000000Z","updated_at":"2023-12-16T08:01:59.000000Z","full_name":"Paulo Mabutol A."},"document_type":{"id":2,"name":"COG","created_at":"2023-12-16T08:02:22.000000Z","updated_at":"2023-12-16T08:02:22.000000Z"}},{"id":1,"ref_id":"657c02d7c6181","document_type_id":1,"user_id":11,"user_info_id":1,"path":"657c02d7c6181.pdf","pushed":1,"created_at":"2023-12-15T07:40:07.000000Z","updated_at":"2023-12-16T08:03:19.000000Z","user":{"id":11,"name":"Test User","email":"test@example.com","email_verified_at":"2023-12-15T07:37:53.000000Z","two_factor_confirmed_at":null,"current_team_id":null,"profile_photo_path":null,"created_at":"2023-12-15T07:37:53.000000Z","updated_at":"2023-12-15T07:37:53.000000Z","profile_photo_url":"https:\/\/ui-avatars.com\/api\/?name=T+U&color=7F9CF5&background=EBF4FF"},"user_info":{"id":1,"firstname":"Jane","lastname":"Doe","middlename":"N\/A","contact":"4223423423","birthdate":"2023-12-12","address":"234234234","created_at":"2023-12-15T07:39:41.000000Z","updated_at":"2023-12-15T07:39:41.000000Z","full_name":"Jane Doe"},"document_type":{"id":1,"name":"COE","created_at":"2023-12-15T07:39:54.000000Z","updated_at":"2023-12-15T07:39:54.000000Z"}},{"id":2,"ref_id":"657d59ba94698","document_type_id":2,"user_id":12,"user_info_id":2,"path":"657d59ba94698.pdf","pushed":1,"created_at":"2023-12-16T08:03:06.000000Z","updated_at":"2023-12-16T08:03:19.000000Z","user":{"id":12,"name":"Daniel Cuevas","email":"cuevas@gmail.com","email_verified_at":null,"two_factor_confirmed_at":null,"current_team_id":null,"profile_photo_path":null,"created_at":"2023-12-16T07:59:56.000000Z","updated_at":"2023-12-16T07:59:56.000000Z","profile_photo_url":"https:\/\/ui-avatars.com\/api\/?name=D+C&color=7F9CF5&background=EBF4FF"},"user_info":{"id":2,"firstname":"Paulo","lastname":"Mabutol","middlename":"A","contact":"ghfhgfhgftyryt","birthdate":"2023-12-01","address":"gjyjygyjjhgyh","created_at":"2023-12-16T08:01:59.000000Z","updated_at":"2023-12-16T08:01:59.000000Z","full_name":"Paulo Mabutol A."},"document_type":{"id":2,"name":"COG","created_at":"2023-12-16T08:02:22.000000Z","updated_at":"2023-12-16T08:02:22.000000Z"}},{"id":1,"ref_id":"657c02d7c6181","document_type_id":1,"user_id":11,"user_info_id":1,"path":"657c02d7c6181.pdf","pushed":1,"created_at":"2023-12-15T07:40:07.000000Z","updated_at":"2023-12-16T08:10:06.000000Z","user":{"id":11,"name":"Test User","email":"test@example.com","email_verified_at":"2023-12-15T07:37:53.000000Z","two_factor_confirmed_at":null,"current_team_id":null,"profile_photo_path":null,"created_at":"2023-12-15T07:37:53.000000Z","updated_at":"2023-12-15T07:37:53.000000Z","profile_photo_url":"https:\/\/ui-avatars.com\/api\/?name=T+U&color=7F9CF5&background=EBF4FF"},"user_info":{"id":1,"firstname":"Jane","lastname":"Doe","middlename":"N\/A","contact":"4223423423","birthdate":"2023-12-12","address":"234234234","created_at":"2023-12-15T07:39:41.000000Z","updated_at":"2023-12-15T07:39:41.000000Z","full_name":"Jane Doe"},"document_type":{"id":1,"name":"COE","created_at":"2023-12-15T07:39:54.000000Z","updated_at":"2023-12-15T07:39:54.000000Z"}},{"id":2,"ref_id":"657d59ba94698","document_type_id":2,"user_id":12,"user_info_id":2,"path":"657d59ba94698.pdf","pushed":1,"created_at":"2023-12-16T08:03:06.000000Z","updated_at":"2023-12-16T08:10:07.000000Z","user":{"id":12,"name":"Daniel Cuevas","email":"cuevas@gmail.com","email_verified_at":null,"two_factor_confirmed_at":null,"current_team_id":null,"profile_photo_path":null,"created_at":"2023-12-16T07:59:56.000000Z","updated_at":"2023-12-16T07:59:56.000000Z","profile_photo_url":"https:\/\/ui-avatars.com\/api\/?name=D+C&color=7F9CF5&background=EBF4FF"},"user_info":{"id":2,"firstname":"Paulo","lastname":"Mabutol","middlename":"A","contact":"ghfhgfhgftyryt","birthdate":"2023-12-01","address":"gjyjygyjjhgyh","created_at":"2023-12-16T08:01:59.000000Z","updated_at":"2023-12-16T08:01:59.000000Z","full_name":"Paulo Mabutol A."},"document_type":{"id":2,"name":"COG","created_at":"2023-12-16T08:02:22.000000Z","updated_at":"2023-12-16T08:02:22.000000Z"}},{"id":1,"ref_id":"657c02d7c6181","document_type_id":1,"user_id":11,"user_info_id":1,"path":"657c02d7c6181.pdf","pushed":1,"created_at":"2023-12-15T07:40:07.000000Z","updated_at":"2023-12-16T08:11:53.000000Z","user":{"id":11,"name":"Test User","email":"test@example.com","email_verified_at":"2023-12-15T07:37:53.000000Z","two_factor_confirmed_at":null,"current_team_id":null,"profile_photo_path":null,"created_at":"2023-12-15T07:37:53.000000Z","updated_at":"2023-12-15T07:37:53.000000Z","profile_photo_url":"https:\/\/ui-avatars.com\/api\/?name=T+U&color=7F9CF5&background=EBF4FF"},"user_info":{"id":1,"firstname":"Jane","lastname":"Doe","middlename":"N\/A","contact":"4223423423","birthdate":"2023-12-12","address":"234234234","created_at":"2023-12-15T07:39:41.000000Z","updated_at":"2023-12-15T07:39:41.000000Z","full_name":"Jane Doe"},"document_type":{"id":1,"name":"COE","created_at":"2023-12-15T07:39:54.000000Z","updated_at":"2023-12-15T07:39:54.000000Z"}},{"id":2,"ref_id":"657d59ba94698","document_type_id":2,"user_id":12,"user_info_id":2,"path":"657d59ba94698.pdf","pushed":1,"created_at":"2023-12-16T08:03:06.000000Z","updated_at":"2023-12-16T08:11:54.000000Z","user":{"id":12,"name":"Daniel Cuevas","email":"cuevas@gmail.com","email_verified_at":null,"two_factor_confirmed_at":null,"current_team_id":null,"profile_photo_path":null,"created_at":"2023-12-16T07:59:56.000000Z","updated_at":"2023-12-16T08:31:29.000000Z","profile_photo_url":"https:\/\/ui-avatars.com\/api\/?name=D+C&color=7F9CF5&background=EBF4FF"},"user_info":{"id":2,"firstname":"Paulo","lastname":"Mabutol","middlename":"A","contact":"ghfhgfhgftyryt","birthdate":"2023-12-01","address":"gjyjygyjjhgyh","created_at":"2023-12-16T08:01:59.000000Z","updated_at":"2023-12-16T08:01:59.000000Z","full_name":"Paulo Mabutol A."},"document_type":{"id":2,"name":"COG","created_at":"2023-12-16T08:02:22.000000Z","updated_at":"2023-12-16T08:02:22.000000Z"}},{"id":3,"ref_id":"657d6355ae2fe","document_type_id":3,"user_id":13,"user_info_id":3,"path":"657d6355ae2fe.pdf","pushed":0,"created_at":"2023-12-16T08:44:05.000000Z","updated_at":"2023-12-16T08:44:23.000000Z","user":{"id":13,"name":"Remric Paderes","email":"remricpaderes@gmail.com","email_verified_at":null,"two_factor_confirmed_at":null,"current_team_id":null,"profile_photo_path":null,"created_at":"2023-12-16T08:38:46.000000Z","updated_at":"2023-12-16T08:38:46.000000Z","profile_photo_url":"https:\/\/ui-avatars.com\/api\/?name=R+P&color=7F9CF5&background=EBF4FF"},"user_info":{"id":3,"firstname":"Remric","lastname":"Psderes","middlename":"m","contact":"09351092248","birthdate":"2023-12-01","address":"penaranda nueva ecija","created_at":"2023-12-16T08:43:20.000000Z","updated_at":"2023-12-16T08:43:20.000000Z","full_name":"Remric Psderes M."},"document_type":{"id":3,"name":"COR","created_at":"2023-12-16T08:43:51.000000Z","updated_at":"2023-12-16T08:43:51.000000Z"}},{"id":1,"ref_id":"657c02d7c6181","document_type_id":1,"user_id":11,"user_info_id":1,"path":"657c02d7c6181.pdf","pushed":1,"created_at":"2023-12-15T07:40:07.000000Z","updated_at":"2023-12-16T08:46:35.000000Z","user":{"id":11,"name":"Test User","email":"test@example.com","email_verified_at":"2023-12-15T07:37:53.000000Z","two_factor_confirmed_at":null,"current_team_id":null,"profile_photo_path":null,"created_at":"2023-12-15T07:37:53.000000Z","updated_at":"2023-12-15T07:37:53.000000Z","profile_photo_url":"https:\/\/ui-avatars.com\/api\/?name=T+U&color=7F9CF5&background=EBF4FF"},"user_info":null,"document_type":{"id":1,"name":"COE","created_at":"2023-12-15T07:39:54.000000Z","updated_at":"2023-12-15T07:39:54.000000Z"}},{"id":2,"ref_id":"657d59ba94698","document_type_id":2,"user_id":12,"user_info_id":2,"path":"657d59ba94698.pdf","pushed":1,"created_at":"2023-12-16T08:03:06.000000Z","updated_at":"2023-12-16T08:46:35.000000Z","user":{"id":12,"name":"Daniel Cuevas","email":"cuevas@gmail.com","email_verified_at":null,"two_factor_confirmed_at":null,"current_team_id":null,"profile_photo_path":null,"created_at":"2023-12-16T07:59:56.000000Z","updated_at":"2023-12-16T08:31:29.000000Z","profile_photo_url":"https:\/\/ui-avatars.com\/api\/?name=D+C&color=7F9CF5&background=EBF4FF"},"user_info":{"id":2,"firstname":"Paulo","lastname":"Mabutol","middlename":"A","contact":"ghfhgfhgftyryt","birthdate":"2023-12-01","address":"gjyjygyjjhgyh","created_at":"2023-12-16T08:01:59.000000Z","updated_at":"2023-12-16T08:01:59.000000Z","full_name":"Paulo Mabutol A."},"document_type":{"id":2,"name":"COG","created_at":"2023-12-16T08:02:22.000000Z","updated_at":"2023-12-16T08:02:22.000000Z"}},{"id":3,"ref_id":"657d6355ae2fe","document_type_id":3,"user_id":13,"user_info_id":3,"path":"657d6355ae2fe.pdf","pushed":1,"created_at":"2023-12-16T08:44:05.000000Z","updated_at":"2023-12-16T08:46:35.000000Z","user":{"id":13,"name":"Remric Paderes","email":"remricpaderes@gmail.com","email_verified_at":null,"two_factor_confirmed_at":null,"current_team_id":null,"profile_photo_path":null,"created_at":"2023-12-16T08:38:46.000000Z","updated_at":"2023-12-16T08:38:46.000000Z","profile_photo_url":"https:\/\/ui-avatars.com\/api\/?name=R+P&color=7F9CF5&background=EBF4FF"},"user_info":{"id":3,"firstname":"Remric","lastname":"Psderes","middlename":"m","contact":"09351092248","birthdate":"2023-12-01","address":"penaranda nueva ecija","created_at":"2023-12-16T08:43:20.000000Z","updated_at":"2023-12-16T08:43:20.000000Z","full_name":"Remric Psderes M."},"document_type":{"id":3,"name":"COR","created_at":"2023-12-16T08:43:51.000000Z","updated_at":"2023-12-16T08:43:51.000000Z"}},{"id":4,"ref_id":"657d6872e5447","document_type_id":3,"user_id":12,"user_info_id":2,"path":"657d6872e5447.pdf","pushed":0,"created_at":"2023-12-16T09:05:54.000000Z","updated_at":"2023-12-16T09:05:55.000000Z","user":{"id":12,"name":"Daniel Cuevas","email":"cuevas@gmail.com","email_verified_at":null,"two_factor_confirmed_at":null,"current_team_id":null,"profile_photo_path":null,"created_at":"2023-12-16T07:59:56.000000Z","updated_at":"2023-12-16T08:31:29.000000Z","profile_photo_url":"https:\/\/ui-avatars.com\/api\/?name=D+C&color=7F9CF5&background=EBF4FF"},"user_info":{"id":2,"firstname":"Paulo","lastname":"Mabutol","middlename":"A","contact":"ghfhgfhgftyryt","birthdate":"2023-12-01","address":"gjyjygyjjhgyh","created_at":"2023-12-16T08:01:59.000000Z","updated_at":"2023-12-16T08:01:59.000000Z","full_name":"Paulo Mabutol A."},"document_type":{"id":3,"name":"COR","created_at":"2023-12-16T08:43:51.000000Z","updated_at":"2023-12-16T08:43:51.000000Z"}},{"id":1,"ref_id":"657c02d7c6181","document_type_id":1,"user_id":11,"user_info_id":1,"path":"657c02d7c6181.pdf","pushed":1,"created_at":"2023-12-15T07:40:07.000000Z","updated_at":"2023-12-16T09:06:00.000000Z","user":{"id":11,"name":"Test User","email":"test@example.com","email_verified_at":"2023-12-15T07:37:53.000000Z","two_factor_confirmed_at":null,"current_team_id":null,"profile_photo_path":null,"created_at":"2023-12-15T07:37:53.000000Z","updated_at":"2023-12-15T07:37:53.000000Z","profile_photo_url":"https:\/\/ui-avatars.com\/api\/?name=T+U&color=7F9CF5&background=EBF4FF"},"user_info":null,"document_type":{"id":1,"name":"COE","created_at":"2023-12-15T07:39:54.000000Z","updated_at":"2023-12-15T07:39:54.000000Z"}},{"id":2,"ref_id":"657d59ba94698","document_type_id":2,"user_id":12,"user_info_id":2,"path":"657d59ba94698.pdf","pushed":1,"created_at":"2023-12-16T08:03:06.000000Z","updated_at":"2023-12-16T09:06:00.000000Z","user":{"id":12,"name":"Daniel Cuevas","email":"cuevas@gmail.com","email_verified_at":null,"two_factor_confirmed_at":null,"current_team_id":null,"profile_photo_path":null,"created_at":"2023-12-16T07:59:56.000000Z","updated_at":"2023-12-16T08:31:29.000000Z","profile_photo_url":"https:\/\/ui-avatars.com\/api\/?name=D+C&color=7F9CF5&background=EBF4FF"},"user_info":null,"document_type":{"id":2,"name":"COG","created_at":"2023-12-16T08:02:22.000000Z","updated_at":"2023-12-16T08:02:22.000000Z"}},{"id":3,"ref_id":"657d6355ae2fe","document_type_id":3,"user_id":13,"user_info_id":3,"path":"657d6355ae2fe.pdf","pushed":1,"created_at":"2023-12-16T08:44:05.000000Z","updated_at":"2023-12-16T09:06:00.000000Z","user":{"id":13,"name":"Remric Paderes","email":"remricpaderes@gmail.com","email_verified_at":null,"two_factor_confirmed_at":null,"current_team_id":null,"profile_photo_path":null,"created_at":"2023-12-16T08:38:46.000000Z","updated_at":"2023-12-16T08:38:46.000000Z","profile_photo_url":"https:\/\/ui-avatars.com\/api\/?name=R+P&color=7F9CF5&background=EBF4FF"},"user_info":null,"document_type":{"id":3,"name":"COR","created_at":"2023-12-16T08:43:51.000000Z","updated_at":"2023-12-16T08:43:51.000000Z"}},{"id":4,"ref_id":"657d6872e5447","document_type_id":3,"user_id":12,"user_info_id":2,"path":"657d6872e5447.pdf","pushed":1,"created_at":"2023-12-16T09:05:54.000000Z","updated_at":"2023-12-16T09:06:00.000000Z","user":{"id":12,"name":"Daniel Cuevas","email":"cuevas@gmail.com","email_verified_at":null,"two_factor_confirmed_at":null,"current_team_id":null,"profile_photo_path":null,"created_at":"2023-12-16T07:59:56.000000Z","updated_at":"2023-12-16T08:31:29.000000Z","profile_photo_url":"https:\/\/ui-avatars.com\/api\/?name=D+C&color=7F9CF5&background=EBF4FF"},"user_info":null,"document_type":{"id":3,"name":"COR","created_at":"2023-12-16T08:43:51.000000Z","updated_at":"2023-12-16T08:43:51.000000Z"}},{"id":5,"ref_id":"657ee79e69171","document_type_id":1,"user_id":12,"user_info_id":10,"path":"657ee79e69171.pdf","pushed":0,"created_at":"2023-12-17T12:20:46.000000Z","updated_at":"2023-12-17T12:20:47.000000Z","user":{"id":12,"name":"Daniel Cuevas","email":"cuevas@gmail.com","email_verified_at":null,"two_factor_confirmed_at":null,"current_team_id":null,"profile_photo_path":null,"created_at":"2023-12-16T07:59:56.000000Z","updated_at":"2023-12-16T08:31:29.000000Z","profile_photo_url":"https:\/\/ui-avatars.com\/api\/?name=D+C&color=7F9CF5&background=EBF4FF"},"user_info":{"id":10,"firstname":"John Russel","lastname":"Mercado","middlename":"M","contact":"09562071914","birthdate":"2023-12-13","address":"gapan city","created_at":"2023-12-17T12:20:07.000000Z","updated_at":"2023-12-17T12:20:07.000000Z","full_name":"John Russel Mercado M."},"document_type":{"id":1,"name":"COE","created_at":"2023-12-15T07:39:54.000000Z","updated_at":"2023-12-15T07:39:54.000000Z"}},{"id":1,"ref_id":"657c02d7c6181","document_type_id":1,"user_id":11,"user_info_id":1,"path":"657c02d7c6181.pdf","pushed":1,"created_at":"2023-12-15T07:40:07.000000Z","updated_at":"2023-12-17T12:20:51.000000Z","user":{"id":11,"name":"Test User","email":"test@example.com","email_verified_at":"2023-12-15T07:37:53.000000Z","two_factor_confirmed_at":null,"current_team_id":null,"profile_photo_path":null,"created_at":"2023-12-15T07:37:53.000000Z","updated_at":"2023-12-15T07:37:53.000000Z","profile_photo_url":"https:\/\/ui-avatars.com\/api\/?name=T+U&color=7F9CF5&background=EBF4FF"},"user_info":null,"document_type":{"id":1,"name":"COE","created_at":"2023-12-15T07:39:54.000000Z","updated_at":"2023-12-15T07:39:54.000000Z"}},{"id":2,"ref_id":"657d59ba94698","document_type_id":2,"user_id":12,"user_info_id":2,"path":"657d59ba94698.pdf","pushed":1,"created_at":"2023-12-16T08:03:06.000000Z","updated_at":"2023-12-17T12:20:52.000000Z","user":{"id":12,"name":"Daniel Cuevas","email":"cuevas@gmail.com","email_verified_at":null,"two_factor_confirmed_at":null,"current_team_id":null,"profile_photo_path":null,"created_at":"2023-12-16T07:59:56.000000Z","updated_at":"2023-12-16T08:31:29.000000Z","profile_photo_url":"https:\/\/ui-avatars.com\/api\/?name=D+C&color=7F9CF5&background=EBF4FF"},"user_info":null,"document_type":{"id":2,"name":"COG","created_at":"2023-12-16T08:02:22.000000Z","updated_at":"2023-12-16T08:02:22.000000Z"}},{"id":3,"ref_id":"657d6355ae2fe","document_type_id":3,"user_id":13,"user_info_id":3,"path":"657d6355ae2fe.pdf","pushed":1,"created_at":"2023-12-16T08:44:05.000000Z","updated_at":"2023-12-17T12:20:52.000000Z","user":{"id":13,"name":"Remric Paderes","email":"remricpaderes@gmail.com","email_verified_at":null,"two_factor_confirmed_at":null,"current_team_id":null,"profile_photo_path":null,"created_at":"2023-12-16T08:38:46.000000Z","updated_at":"2023-12-16T08:38:46.000000Z","profile_photo_url":"https:\/\/ui-avatars.com\/api\/?name=R+P&color=7F9CF5&background=EBF4FF"},"user_info":null,"document_type":{"id":3,"name":"COR","created_at":"2023-12-16T08:43:51.000000Z","updated_at":"2023-12-16T08:43:51.000000Z"}},{"id":4,"ref_id":"657d6872e5447","document_type_id":3,"user_id":12,"user_info_id":2,"path":"657d6872e5447.pdf","pushed":1,"created_at":"2023-12-16T09:05:54.000000Z","updated_at":"2023-12-17T12:20:52.000000Z","user":{"id":12,"name":"Daniel Cuevas","email":"cuevas@gmail.com","email_verified_at":null,"two_factor_confirmed_at":null,"current_team_id":null,"profile_photo_path":null,"created_at":"2023-12-16T07:59:56.000000Z","updated_at":"2023-12-16T08:31:29.000000Z","profile_photo_url":"https:\/\/ui-avatars.com\/api\/?name=D+C&color=7F9CF5&background=EBF4FF"},"user_info":null,"document_type":{"id":3,"name":"COR","created_at":"2023-12-16T08:43:51.000000Z","updated_at":"2023-12-16T08:43:51.000000Z"}},{"id":5,"ref_id":"657ee79e69171","document_type_id":1,"user_id":12,"user_info_id":10,"path":"657ee79e69171.pdf","pushed":1,"created_at":"2023-12-17T12:20:46.000000Z","updated_at":"2023-12-17T12:20:52.000000Z","user":{"id":12,"name":"Daniel Cuevas","email":"cuevas@gmail.com","email_verified_at":null,"two_factor_confirmed_at":null,"current_team_id":null,"profile_photo_path":null,"created_at":"2023-12-16T07:59:56.000000Z","updated_at":"2023-12-16T08:31:29.000000Z","profile_photo_url":"https:\/\/ui-avatars.com\/api\/?name=D+C&color=7F9CF5&background=EBF4FF"},"user_info":{"id":10,"firstname":"John Russel","lastname":"Mercado","middlename":"M","contact":"09562071914","birthdate":"2023-12-13","address":"gapan city","created_at":"2023-12-17T12:20:07.000000Z","updated_at":"2023-12-17T12:20:07.000000Z","full_name":"John Russel Mercado M."},"document_type":{"id":1,"name":"COE","created_at":"2023-12-15T07:39:54.000000Z","updated_at":"2023-12-15T07:39:54.000000Z"}},{"id":6,"ref_id":"657f07ac0db26","document_type_id":2,"user_id":12,"user_info_id":4,"path":"657f07ac0db26.pdf","pushed":0,"created_at":"2023-12-17T14:37:32.000000Z","updated_at":"2023-12-17T14:37:35.000000Z","user":{"id":12,"name":"Daniel Cuevas","email":"cuevas@gmail.com","email_verified_at":null,"two_factor_confirmed_at":null,"current_team_id":null,"profile_photo_path":null,"created_at":"2023-12-16T07:59:56.000000Z","updated_at":"2023-12-16T08:31:29.000000Z","profile_photo_url":"https:\/\/ui-avatars.com\/api\/?name=D+C&color=7F9CF5&background=EBF4FF"},"user_info":{"id":4,"firstname":"kelly","lastname":"Lim","middlename":"V","contact":"09319230056","birthdate":"2023-12-13","address":"penaranda","created_at":"2023-12-16T11:45:49.000000Z","updated_at":"2023-12-16T11:45:49.000000Z","full_name":"kelly Lim V."},"document_type":{"id":2,"name":"COG","created_at":"2023-12-16T08:02:22.000000Z","updated_at":"2023-12-16T08:02:22.000000Z"}},{"id":1,"ref_id":"657c02d7c6181","document_type_id":1,"user_id":11,"user_info_id":1,"path":"657c02d7c6181.pdf","pushed":1,"created_at":"2023-12-15T07:40:07.000000Z","updated_at":"2023-12-17T14:37:54.000000Z","user":{"id":11,"name":"Test User","email":"test@example.com","email_verified_at":"2023-12-15T07:37:53.000000Z","two_factor_confirmed_at":null,"current_team_id":null,"profile_photo_path":null,"created_at":"2023-12-15T07:37:53.000000Z","updated_at":"2023-12-15T07:37:53.000000Z","profile_photo_url":"https:\/\/ui-avatars.com\/api\/?name=T+U&color=7F9CF5&background=EBF4FF"},"user_info":null,"document_type":{"id":1,"name":"COE","created_at":"2023-12-15T07:39:54.000000Z","updated_at":"2023-12-15T07:39:54.000000Z"}},{"id":2,"ref_id":"657d59ba94698","document_type_id":2,"user_id":12,"user_info_id":2,"path":"657d59ba94698.pdf","pushed":1,"created_at":"2023-12-16T08:03:06.000000Z","updated_at":"2023-12-17T14:37:54.000000Z","user":{"id":12,"name":"Daniel Cuevas","email":"cuevas@gmail.com","email_verified_at":null,"two_factor_confirmed_at":null,"current_team_id":null,"profile_photo_path":null,"created_at":"2023-12-16T07:59:56.000000Z","updated_at":"2023-12-16T08:31:29.000000Z","profile_photo_url":"https:\/\/ui-avatars.com\/api\/?name=D+C&color=7F9CF5&background=EBF4FF"},"user_info":null,"document_type":{"id":2,"name":"COG","created_at":"2023-12-16T08:02:22.000000Z","updated_at":"2023-12-16T08:02:22.000000Z"}},{"id":3,"ref_id":"657d6355ae2fe","document_type_id":3,"user_id":13,"user_info_id":3,"path":"657d6355ae2fe.pdf","pushed":1,"created_at":"2023-12-16T08:44:05.000000Z","updated_at":"2023-12-17T14:37:54.000000Z","user":{"id":13,"name":"Remric Paderes","email":"remricpaderes@gmail.com","email_verified_at":null,"two_factor_confirmed_at":null,"current_team_id":null,"profile_photo_path":null,"created_at":"2023-12-16T08:38:46.000000Z","updated_at":"2023-12-16T08:38:46.000000Z","profile_photo_url":"https:\/\/ui-avatars.com\/api\/?name=R+P&color=7F9CF5&background=EBF4FF"},"user_info":null,"document_type":{"id":3,"name":"COR","created_at":"2023-12-16T08:43:51.000000Z","updated_at":"2023-12-16T08:43:51.000000Z"}},{"id":4,"ref_id":"657d6872e5447","document_type_id":3,"user_id":12,"user_info_id":2,"path":"657d6872e5447.pdf","pushed":1,"created_at":"2023-12-16T09:05:54.000000Z","updated_at":"2023-12-17T14:37:54.000000Z","user":{"id":12,"name":"Daniel Cuevas","email":"cuevas@gmail.com","email_verified_at":null,"two_factor_confirmed_at":null,"current_team_id":null,"profile_photo_path":null,"created_at":"2023-12-16T07:59:56.000000Z","updated_at":"2023-12-16T08:31:29.000000Z","profile_photo_url":"https:\/\/ui-avatars.com\/api\/?name=D+C&color=7F9CF5&background=EBF4FF"},"user_info":null,"document_type":{"id":3,"name":"COR","created_at":"2023-12-16T08:43:51.000000Z","updated_at":"2023-12-16T08:43:51.000000Z"}},{"id":5,"ref_id":"657ee79e69171","document_type_id":1,"user_id":12,"user_info_id":10,"path":"657ee79e69171.pdf","pushed":1,"created_at":"2023-12-17T12:20:46.000000Z","updated_at":"2023-12-17T14:37:54.000000Z","user":{"id":12,"name":"Daniel Cuevas","email":"cuevas@gmail.com","email_verified_at":null,"two_factor_confirmed_at":null,"current_team_id":null,"profile_photo_path":null,"created_at":"2023-12-16T07:59:56.000000Z","updated_at":"2023-12-16T08:31:29.000000Z","profile_photo_url":"https:\/\/ui-avatars.com\/api\/?name=D+C&color=7F9CF5&background=EBF4FF"},"user_info":{"id":10,"firstname":"John Russel","lastname":"Mercado","middlename":"M","contact":"09562071914","birthdate":"2023-12-13","address":"gapan city","created_at":"2023-12-17T12:20:07.000000Z","updated_at":"2023-12-17T12:20:07.000000Z","full_name":"John Russel Mercado M."},"document_type":{"id":1,"name":"COE","created_at":"2023-12-15T07:39:54.000000Z","updated_at":"2023-12-15T07:39:54.000000Z"}},{"id":6,"ref_id":"657f07ac0db26","document_type_id":2,"user_id":12,"user_info_id":4,"path":"657f07ac0db26.pdf","pushed":1,"created_at":"2023-12-17T14:37:32.000000Z","updated_at":"2023-12-17T14:37:54.000000Z","user":{"id":12,"name":"Daniel Cuevas","email":"cuevas@gmail.com","email_verified_at":null,"two_factor_confirmed_at":null,"current_team_id":null,"profile_photo_path":null,"created_at":"2023-12-16T07:59:56.000000Z","updated_at":"2023-12-16T08:31:29.000000Z","profile_photo_url":"https:\/\/ui-avatars.com\/api\/?name=D+C&color=7F9CF5&background=EBF4FF"},"user_info":{"id":4,"firstname":"kelly","lastname":"Lim","middlename":"V","contact":"09319230056","birthdate":"2023-12-13","address":"penaranda","created_at":"2023-12-16T11:45:49.000000Z","updated_at":"2023-12-16T11:45:49.000000Z","full_name":"kelly Lim V."},"document_type":{"id":2,"name":"COG","created_at":"2023-12-16T08:02:22.000000Z","updated_at":"2023-12-16T08:02:22.000000Z"}},{"id":7,"ref_id":"657fb5a12e8f4","document_type_id":3,"user_id":14,"user_info_id":11,"path":"657fb5a12e8f4.pdf","pushed":0,"created_at":"2023-12-18T02:59:45.000000Z","updated_at":"2023-12-18T02:59:48.000000Z","user":{"id":14,"name":"russel malakas","email":"mercadojohnrussel00@gmail.com","email_verified_at":null,"two_factor_confirmed_at":null,"current_team_id":null,"profile_photo_path":null,"created_at":"2023-12-18T02:52:08.000000Z","updated_at":"2023-12-18T02:52:08.000000Z","profile_photo_url":"https:\/\/ui-avatars.com\/api\/?name=r+m&color=7F9CF5&background=EBF4FF"},"user_info":{"id":11,"firstname":"jowel","lastname":"de guzman","middlename":"N\/A","contact":"0953329992","birthdate":"1995-10-07","address":"penaranda","created_at":"2023-12-18T02:54:07.000000Z","updated_at":"2023-12-18T02:54:07.000000Z","full_name":"jowel de guzman"},"document_type":{"id":3,"name":"COR","created_at":"2023-12-16T08:43:51.000000Z","updated_at":"2023-12-16T08:43:51.000000Z"}}]